[
  {
    "page_id": "ce6ef35e",
    "url": "https://www.soprasteria.be/whatwedo/data-ai/data-science-and-ai/the-future-of-generative-ai",
    "slug": "wwwsoprasteriabewhatwedodata-aidata-science-and-aithe-future-of-generative-ai",
    "persona": {
      "name": "The_BENELUX_Technology_Innovation_Leader",
      "description": "Unknown Persona (This persona encompasses Chief Technology Officers (CTOs), Chief Digital Officers (CDOs), and their C-suite peers, such as Chief Information Officers (CIOs). They are typically strategic business leaders responsible for driving growth and transformation through technology.)"
    },
    "hygiene_scorecard": {
      "tier": "Thought",
      "final_score": 7.6,
      "brand_health_index": 6.56,
      "trust_gap": 0.3,
      "audited_ts": "2025-06-21",
      "detailed_scores": {
        "|_corporate_positioning_alignment": {
          "score": 8,
          "rationale": "The page reflects Sopra Steria's positioning as a trusted digital business partner helping organizations harness AI's transformative power. It aligns with their mission to deliver tangible business value through responsible AI. However, it could tie the GenAI insights more explicitly to Sopra Steria's unique approach and capabilities."
        },
        "brand_differentiation": {
          "score": 7,
          "rationale": "The report offers a detailed analysis of the GenAI landscape in 2025, combining insights from various sources and Sopra Steria's AI specialists. This demonstrates their thought leadership and forward-looking perspective. However, the specific ways Sopra Steria is leading in this space could be highlighted more to truly stand out from other IT services firms."
        },
        "value_proposition_clarity": {
          "score": 8,
          "rationale": "The report promises key trends, technological advancements, and strategic recommendations for 2025 related to Generative AI. This is likely highly relevant and valuable for the target CTO/CDO persona looking to understand and capitalize on the future of AI. The specific benefits of partnering with Sopra Steria to navigate this landscape could be articulated more clearly though."
        },
        "trust_&_credibility_signals": {
          "score": 7,
          "rationale": "Leveraging insights from Sopra Steria's AI specialists lends credibility, as does the forward-looking nature of the report. However, more tangible proof points about Sopra Steria's AI track record and client results would enhance trust. Highlighting any 3rd party analyst recognition of their AI capabilities could also boost credibility for this C-suite audience."
        },
        "call-to-action_effectiveness": {
          "score": 8,
          "rationale": "The \"Download Report\" CTA is prominent and relevant for this persona interested in deeply understanding the GenAI future. Offering a consultation with an AI specialist to discuss their specific situation could be a strong secondary CTA to engage them further. The path to becoming an AI-powered organization with Sopra Steria's help could also be articulated to drive next steps."
        }
      },
      "recommendations": []
    },
    "experience_report": {
      "overall_sentiment": "Neutral",
      "engagement_level": "Low",
      "conversion_likelihood": "Low",
      "effective_copy": [
        {
          "text": "\"With our extensive team of data scientists, we use a blend of statistics, mathematics, software engineering, and industry expertise to develop responsible AI-powered solutions that deliver tangible value to your organisation.\"",
          "analysis": "As a technology leader, I appreciate that Sopra Steria highlights their multidisciplinary approach and focus on delivering tangible business value with AI. This aligns with my goal of strategically leveraging AI for measurable impact while ensuring responsible deployment."
        },
        {
          "text": "\"We collaborate with you to identify high-impact use cases and assess ROI throughout the experimentation and production phases.\"",
          "analysis": "As a strategic business leader, ROI is a key consideration in any technology investment. I appreciate that Sopra Steria proactively addresses this and positions themselves as a collaborative partner in identifying high-value AI use cases. This gives me confidence that they understand my business priorities."
        }
      ],
      "ineffective_copy": [
        {
          "text": "\"AI is fundamentally reshaping the way businesses operate and creating new opportunities across industries and markets.\"",
          "analysis": "As a CTO/CDO, this statement is too broad and generic. It lacks specificity on how AI can directly impact my business and drive measurable outcomes. I need more tangible examples relevant to my industry and role."
        },
        {
          "text": "\"Organisations that hesitate to embrace these advances risk falling behind the curve, jeopardising their relevance in an increasingly digital world.\"",
          "analysis": "While the urgency to adopt AI is clear to me as a CTO/CDO, this copy feels alarmist without providing a clear path forward. I would prefer to see more emphasis on the specific benefits and opportunities of embracing AI rather than just the risks of inaction."
        }
      ],
      "first_impression": "",
      "strategic_analysis": ""
    },
    "embeddings_content": {
      "combined_analysis": "HYGIENE SCORECARD:\n# Brand Hygiene Scorecard\n\n**URL:** https://www.soprasteria.be/whatwedo/data-ai/data-science-and-ai/the-future-of-generative-ai\n**Persona:** Unknown Persona (This persona encompasses Chief Technology Officers (CTOs), Chief Digital Officers (CDOs), and their C-suite peers, such as Chief Information Officers (CIOs). They are typically strategic business leaders responsible for driving growth and transformation through technology.)\n**Audited:** 2025-06-21 15:53:45\n\n---\n\n## Overall Assessment\n\n- **Tier/Channel:** Thought Leadership Content Page\n- **Final Score:** 7.6/10\n\n---\n\n## Detailed Scoring\n\n| Category | Score | Rationale |\n| -------- | ----- | --------- |\n| Corporate Positioning Alignment | 8 | The page reflects Sopra Steria's positioning as a trusted digital business partner helping organizations harness AI's transformative power. It aligns with their mission to deliver tangible business value through responsible AI. However, it could tie the GenAI insights more explicitly to Sopra Steria's unique approach and capabilities. |\n| Brand Differentiation | 7 | The report offers a detailed analysis of the GenAI landscape in 2025, combining insights from various sources and Sopra Steria's AI specialists. This demonstrates their thought leadership and forward-looking perspective. However, the specific ways Sopra Steria is leading in this space could be highlighted more to truly stand out from other IT services firms. |\n| Value Proposition Clarity | 8 | The report promises key trends, technological advancements, and strategic recommendations for 2025 related to Generative AI. This is likely highly relevant and valuable for the target CTO/CDO persona looking to understand and capitalize on the future of AI. The specific benefits of partnering with Sopra Steria to navigate this landscape could be articulated more clearly though. |\n| Trust & Credibility Signals | 7 | Leveraging insights from Sopra Steria's AI specialists lends credibility, as does the forward-looking nature of the report. However, more tangible proof points about Sopra Steria's AI track record and client results would enhance trust. Highlighting any 3rd party analyst recognition of their AI capabilities could also boost credibility for this C-suite audience. |\n| Call-to-Action Effectiveness | 8 | The \"Download Report\" CTA is prominent and relevant for this persona interested in deeply understanding the GenAI future. Offering a consultation with an AI specialist to discuss their specific situation could be a strong secondary CTA to engage them further. The path to becoming an AI-powered organization with Sopra Steria's help could also be articulated to drive next steps. |\n\n---\n\n## Summary Rationale\n\nOverall, this Future of Generative AI report page is well-aligned to the needs and priorities of a CTO/CDO persona. It demonstrates Sopra Steria's thought leadership and ability to guide clients into the AI-powered future, which is likely top of mind for these executives. \n\nThe key strengths are the forward-looking insights, specialist expertise, and focus on responsible AI adoption. To truly impress this audience though, the page could work harder to prove Sopra Steria's unique AI capabilities and client successes. The CTA is on point, but the next steps in the buyer's journey could be better defined.\n\nWith some refinement to better differentiate the Sopra Steria brand and make a stronger business case for partnering with them, this page could be an even more powerful tool to engage and convert this critical C-suite persona.\n\n---\n\n## Priority Recommendations\n\n1. **Highlight Sopra Steria's unique AI approach/assets** - Weave in more proof points on Sopra Steria's specific AI methodology, technology, talent, and results to differentiate from other players and showcase their edge.\n\n2. **Strengthen trust and credibility** - Feature any 3rd party validation of Sopra Steria's AI capabilities, such as analyst reports or awards. Highlight impressive client stats or case studies.\n\n3. **Clarify next steps** - Beyond the report download, suggest additional relevant content and make a strong case for engaging Sopra Steria to help define their AI strategy and roadmap. Paint the picture of the transformation journey.\n\nEXPERIENCE REPORT:\n| Finding          | Example from Text | Strategic Analysis (from Persona's View)            |\n| ---------------- | ----------------- | --------------------------------------------------- |\n| Ineffective Copy | \"AI is fundamentally reshaping the way businesses operate and creating new opportunities across industries and markets.\"      | As a CTO/CDO, this statement is too broad and generic. It lacks specificity on how AI can directly impact my business and drive measurable outcomes. I need more tangible examples relevant to my industry and role. |\n| Effective Copy   | \"With our extensive team of data scientists, we use a blend of statistics, mathematics, software engineering, and industry expertise to develop responsible AI-powered solutions that deliver tangible value to your organisation.\"      | As a technology leader, I appreciate that Sopra Steria highlights their multidisciplinary approach and focus on delivering tangible business value with AI. This aligns with my goal of strategically leveraging AI for measurable impact while ensuring responsible deployment.    |\n| Ineffective Copy | \"Organisations that hesitate to embrace these advances risk falling behind the curve, jeopardising their relevance in an increasingly digital world.\" | While the urgency to adopt AI is clear to me as a CTO/CDO, this copy feels alarmist without providing a clear path forward. I would prefer to see more emphasis on the specific benefits and opportunities of embracing AI rather than just the risks of inaction. |\n| Effective Copy | \"We collaborate with you to identify high-impact use cases and assess ROI throughout the experimentation and production phases.\" | As a strategic business leader, ROI is a key consideration in any technology investment. I appreciate that Sopra Steria proactively addresses this and positions themselves as a collaborative partner in identifying high-value AI use cases. This gives me confidence that they understand my business priorities.|\n\n**First-Person Narrative Analysis:**\n\nAs a CTO/CDO responsible for driving digital transformation, my first impression of this webpage is mixed. While Sopra Steria clearly positions themselves as an AI partner for businesses, the overall messaging feels somewhat generic and high-level for my needs. I would prefer to see more specific, industry-relevant examples of how their AI solutions have driven measurable business outcomes for organizations like mine. \n\nThe language is professional and touches on some key priorities for technology leaders, such as responsible AI deployment and delivering tangible value. However, it could be more targeted to my specific role and challenges. For example, I would like to see more acknowledgment of the complexities of integrating AI within existing legacy systems and processes, which is a major pain point for many CTOs/CDOs.\n\nIn terms of gaps, I would need more information on Sopra Steria's specific AI capabilities, methodologies, and track record to fully evaluate their potential as a strategic partner. Case studies, client testimonials, or quantitative proof points could help build trust and credibility here. I also want to better understand their approach to key issues like data governance, ethics, and security, which are critical considerations in any AI deployment.\n\nOverall, while this page demonstrates Sopra Steria's high-level AI expertise, it falls short of fully convincing me as a CTO/CDO to engage their services. To improve, I recommend:\n\n1. Tailoring the messaging more directly to the needs and priorities of technology leaders like myself \n2. Providing more concrete, industry-specific examples of AI success stories\n3. Delving deeper into their capabilities around responsible AI, data management, and integration with existing systems\n4. Including more trust-building elements like client proof points, security certifications, or thought leadership content\n\nWith these enhancements, the page could more effectively speak to CTOs/CDOs and drive productive business conversations around AI partnership opportunities.",
      "key_themes": [
        "trust",
        "security",
        "innovation",
        "risk"
      ],
      "business_impact": ""
    },
    "metadata": {
      "persona_id": "the_benelux_technology_innovation_leader",
      "page_id": "ce6ef35e",
      "tier": "thought",
      "final_score": 7.6,
      "domain": "www.soprasteria.be",
      "content_type": "service",
      "regulatory_frameworks": [],
      "is_benelux": true,
      "has_compliance_content": false,
      "has_security_content": true,
      "compiled_at": "2025-07-03T07:43:07.392177"
    }
  },
  {
    "page_id": "2aa6d30b",
    "url": "https://www.soprasteria.com/about-us/corporate-responsibility",
    "slug": "wwwsoprasteriacomabout-uscorporate-responsibility",
    "persona": {
      "name": "The_BENELUX_Technology_Innovation_Leader",
      "description": "Unknown Persona (This persona encompasses Chief Technology Officers (CTOs), Chief Digital Officers (CDOs), and their C-suite peers, such as Chief Information Officers (CIOs). They are typically strategic business leaders responsible for driving growth and transformation through technology.)"
    },
    "hygiene_scorecard": {
      "tier": "Corporate",
      "final_score": 7.4,
      "brand_health_index": 6.44,
      "trust_gap": 0.2,
      "audited_ts": "2025-06-21",
      "detailed_scores": {
        "|_corporate_positioning_alignment": {
          "score": 8,
          "rationale": "The page effectively communicates Sopra Steria's commitment to corporate responsibility and sustainable practices, which aligns well with the company's core brand message of \"building a positive future for all\". Key evidence includes the CEO quote emphasizing a \"sustainable, human‑centred, and guiding contribution\" and sections detailing environmental, social, and ethical commitments."
        },
        "brand_differentiation": {
          "score": 6,
          "rationale": "While the page highlights Sopra Steria's corporate responsibility initiatives, the content feels somewhat generic and lacks strong differentiation from competitors. Statements like being \"convinced that our community makes us stronger\" and supporting \"community projects assisting the vulnerable\" are admirable but common among socially-conscious companies. More specifics on unique programs would enhance differentiation."
        },
        "value_proposition_clarity": {
          "score": 7,
          "rationale": "For a CTO/CDO persona, the value proposition around Sopra Steria's corporate responsibility is implied but not explicitly stated. Content like helping clients \"address sustainable development challenges as an integral part of their digital transformation projects\" hints at the business value, but a clearer articulation of how these efforts drive client success and innovation would strengthen the proposition."
        },
        "trust_&_credibility_signals": {
          "score": 8,
          "rationale": "The page includes several trust-building elements, such as the CEO commitment, specific environmental and social responsibility sections, mention of compliance with \"highest standards of business ethics\", and the Corporate Responsibility Advisory Board. Quantifying impact with stats and adding client testimonials would further boost credibility."
        },
        "call-to-action_effectiveness": {
          "score": 6,
          "rationale": "The \"Find out more\" links for each commitment area provide logical next steps for the persona to explore relevant content. However, the calls-to-action are not particularly compelling for a CTO/CDO. Adding CTAs around connecting with experts on leveraging responsibility practices to drive digital transformation and innovation would be more effective."
        }
      },
      "recommendations": []
    },
    "experience_report": {
      "overall_sentiment": "Neutral",
      "engagement_level": "Low",
      "conversion_likelihood": "Low",
      "effective_copy": [
        {
          "text": "\"We also help our clients to address sustainable development challenges as an integral part of their digital transformation projects.\"",
          "analysis": "As a C-suite technology leader, it's important to me that our partners can help us address sustainability as part of our broader digital transformation efforts. This statement shows Sopra Steria understands the strategic link between these two priorities, which aligns well with my perspective."
        },
        {
          "text": "\"Sopra Steria innovates to support environmental causes as part of an ambitious programme launched over 10 years ago. The Group is a leader in environmental conservation and action against climate change with internationally recognised commitments and results.\"",
          "analysis": "As a technology executive, I'm looking for partners with a proven track record of delivering on their sustainability commitments. The mention of Sopra Steria's long-running program and recognition as an environmental leader helps build credibility that they can support my organization's sustainability goals as part of our technology strategy."
        }
      ],
      "ineffective_copy": [
        {
          "text": "\"We take care to recruit employees from a broad diversity of backgrounds and ensure that we treat everyone fairly.\"",
          "analysis": "As a CTO/CDO focused on driving strategic transformation, this statement about employee diversity and fairness, while positive, does not directly address my key priorities around leveraging technology and AI to create business value. It lacks a clear connection to my role and goals."
        },
        {
          "text": "\"Sopra Steria strives for a more inclusive and ethical digital society, in keeping with its mission: leverage digital technology to build a positive future for all.\"",
          "analysis": "While I appreciate the aspirational vision, as a CTO/CDO I need more specifics on how Sopra Steria will tangibly help my organization leverage technology to drive business outcomes. The language here is quite broad and doesn't speak directly to my role and priorities."
        }
      ],
      "first_impression": "",
      "strategic_analysis": ""
    },
    "embeddings_content": {
      "combined_analysis": "HYGIENE SCORECARD:\n# Brand Hygiene Scorecard\n\n**URL:** https://www.soprasteria.com/about-us/corporate-responsibility\n**Persona:** Unknown Persona (This persona encompasses Chief Technology Officers (CTOs), Chief Digital Officers (CDOs), and their C-suite peers, such as Chief Information Officers (CIOs). They are typically strategic business leaders responsible for driving growth and transformation through technology.)\n**Audited:** 2025-06-21 15:51:24\n\n---\n\n## Overall Assessment\n\n- **Tier/Channel:** Corporate Responsibility Overview Page \n- **Final Score:** 7.4/10\n\n---\n\n## Detailed Scoring\n\n| Category | Score | Rationale |\n| -------- | ----- | --------- |\n| Corporate Positioning Alignment | 8 | The page effectively communicates Sopra Steria's commitment to corporate responsibility and sustainable practices, which aligns well with the company's core brand message of \"building a positive future for all\". Key evidence includes the CEO quote emphasizing a \"sustainable, human‑centred, and guiding contribution\" and sections detailing environmental, social, and ethical commitments. |\n| Brand Differentiation | 6 | While the page highlights Sopra Steria's corporate responsibility initiatives, the content feels somewhat generic and lacks strong differentiation from competitors. Statements like being \"convinced that our community makes us stronger\" and supporting \"community projects assisting the vulnerable\" are admirable but common among socially-conscious companies. More specifics on unique programs would enhance differentiation. |\n| Value Proposition Clarity | 7 | For a CTO/CDO persona, the value proposition around Sopra Steria's corporate responsibility is implied but not explicitly stated. Content like helping clients \"address sustainable development challenges as an integral part of their digital transformation projects\" hints at the business value, but a clearer articulation of how these efforts drive client success and innovation would strengthen the proposition. |\n| Trust & Credibility Signals | 8 | The page includes several trust-building elements, such as the CEO commitment, specific environmental and social responsibility sections, mention of compliance with \"highest standards of business ethics\", and the Corporate Responsibility Advisory Board. Quantifying impact with stats and adding client testimonials would further boost credibility. |  \n| Call-to-Action Effectiveness | 6 | The \"Find out more\" links for each commitment area provide logical next steps for the persona to explore relevant content. However, the calls-to-action are not particularly compelling for a CTO/CDO. Adding CTAs around connecting with experts on leveraging responsibility practices to drive digital transformation and innovation would be more effective. |\n\n---\n\n## Summary Rationale\n\nFor a CTO/CDO persona, this Corporate Responsibility overview page scores well on communicating Sopra Steria's commitment to sustainable practices and ethical principles (8/10) with reasonable trust and credibility signals (8/10). \n\nHowever, the page falls short on clearly differentiating Sopra Steria's corporate responsibility approach from competitors (6/10) and articulating a compelling value proposition for technology leaders (7/10). The calls-to-action, while present, lack persona-specific relevance and impact (6/10).\n\nOverall, the page is professional and aligned with Sopra Steria's brand, but has room for improvement in speaking directly to CTO/CDO priorities around innovation, transformation and demonstrable business value. With an average score of 7.4, it meets persona needs but doesn't quite stand out as an exceptional, persona-optimized resource.\n\n---\n\n## Priority Recommendations\n\n1. **Strengthen differentiation** - Highlight unique and innovative corporate responsibility initiatives that set Sopra Steria apart, especially those enabled by the company's technology capabilities. \n\n2. **Clarify CTO/CDO value proposition** - Explicitly connect corporate responsibility efforts to driving client digital transformation, innovation, and business outcomes. Provide proof points.\n\n3. **Optimize calls-to-action** - Include CTAs tailored to CTO/CDO interests, such as \"Explore how our sustainable practices accelerate client innovation\" or \"Connect with an expert on embedding responsibility into digital transformation\".\n\nEXPERIENCE REPORT:\n| Finding          | Example from Text | Strategic Analysis (from Persona's View)            |\n| ---------------- | ----------------- | --------------------------------------------------- |\n| Ineffective Copy | \"We take care to recruit employees from a broad diversity of backgrounds and ensure that we treat everyone fairly.\"      | As a CTO/CDO focused on driving strategic transformation, this statement about employee diversity and fairness, while positive, does not directly address my key priorities around leveraging technology and AI to create business value. It lacks a clear connection to my role and goals. |\n| Effective Copy   | \"We also help our clients to address sustainable development challenges as an integral part of their digital transformation projects.\"      | As a C-suite technology leader, it's important to me that our partners can help us address sustainability as part of our broader digital transformation efforts. This statement shows Sopra Steria understands the strategic link between these two priorities, which aligns well with my perspective.    |\n| Ineffective Copy | \"Sopra Steria strives for a more inclusive and ethical digital society, in keeping with its mission: leverage digital technology to build a positive future for all.\"      | While I appreciate the aspirational vision, as a CTO/CDO I need more specifics on how Sopra Steria will tangibly help my organization leverage technology to drive business outcomes. The language here is quite broad and doesn't speak directly to my role and priorities. |\n| Effective Copy   | \"Sopra Steria innovates to support environmental causes as part of an ambitious programme launched over 10 years ago. The Group is a leader in environmental conservation and action against climate change with internationally recognised commitments and results.\"      | As a technology executive, I'm looking for partners with a proven track record of delivering on their sustainability commitments. The mention of Sopra Steria's long-running program and recognition as an environmental leader helps build credibility that they can support my organization's sustainability goals as part of our technology strategy.    |\n\nFirst-Person Narrative Analysis:\n\nAs a CTO/CDO, my first impression of this Corporate Responsibility page is mixed. While Sopra Steria clearly has a strong commitment to sustainability and social responsibility, the framing and language don't consistently speak to my specific priorities around leveraging technology to drive strategic business value. I appreciate the mentions of helping clients address sustainable development challenges as part of digital transformation projects - this shows an understanding of how these efforts need to be integrated. However, I would have liked to see more explicit examples of how their capabilities in AI, data, and emerging technologies are being applied to create tangible business and sustainability outcomes for organizations like mine.\n\nThe aspirational language around building a more inclusive digital society, while admirable, doesn't provide me with a clear sense of how they can help me navigate key challenges like legacy modernization, budget constraints, and talent shortages as I seek to aggressively adopt AI and other technologies. I'd need more specifics around their offerings, methodologies, and track record of delivering results for companies in my industry and region.\n\nThat said, the page does build some credibility by highlighting Sopra Steria's long-standing commitment to sustainability, ambitious net zero program, and recognition as an environmental leader. The Corporate Responsibility Advisory Board also adds legitimacy. To strengthen trust and connection with senior technology decision-makers like myself, I'd recommend Sopra Steria bring in more proof points and examples showcasing transformative client results achieved through the innovative application of technology. Framing their sustainability efforts more through the lens of business strategy and impact would also help this page resonate more strongly with my C-suite peers and me. With some tweaks to better address my priorities and pain points, this page could more effectively position Sopra Steria as a compelling potential partner in driving sustainable technology-enabled growth.",
      "key_themes": [
        "trust",
        "compliance",
        "innovation"
      ],
      "business_impact": ""
    },
    "metadata": {
      "persona_id": "the_benelux_technology_innovation_leader",
      "page_id": "2aa6d30b",
      "tier": "corporate",
      "final_score": 7.4,
      "domain": "www.soprasteria.com",
      "content_type": "corporate",
      "regulatory_frameworks": [],
      "is_benelux": false,
      "has_compliance_content": true,
      "has_security_content": false,
      "compiled_at": "2025-07-03T07:43:07.393640"
    }
  },
  {
    "page_id": "fe8eb8c2",
    "url": "https://www.soprasteria.nl/newsroom/blog/details/ecosystems-yes-please-but-how-can-we-trust-each-other",
    "slug": "wwwsoprasterianlnewsroomblogdetailsecosystems-yes-please-but-how-can-we-trust-each-other",
    "persona": {
      "name": "The_BENELUX_Technology_Innovation_Leader",
      "description": "Unknown Persona (This persona encompasses Chief Technology Officers (CTOs), Chief Digital Officers (CDOs), and their C-suite peers, such as Chief Information Officers (CIOs). They are typically strategic business leaders responsible for driving growth and transformation through technology.)"
    },
    "hygiene_scorecard": {
      "tier": "Thought",
      "final_score": 7.4,
      "brand_health_index": 6.44,
      "trust_gap": 0.2,
      "audited_ts": "2025-06-21",
      "detailed_scores": {
        "|_corporate_positioning_alignment": {
          "score": 8,
          "rationale": "The blog post aligns well with Sopra Steria's positioning as a digital transformation partner, discussing how to build resilient supply chain ecosystems through technology. It showcases their expertise in data platforms, cybersecurity, and industry knowledge."
        },
        "brand_differentiation": {
          "score": 6,
          "rationale": "While the content demonstrates Sopra Steria's capabilities, it lacks strong differentiation from competitors. The insights, while valuable, are relatively generic and could apply to many technology consulting firms. More unique Sopra Steria IP or methodologies would strengthen differentiation."
        },
        "value_proposition_clarity": {
          "score": 7,
          "rationale": "The post articulates a clear value proposition around building collaborative, data-driven supply chain ecosystems to drive efficiency, resilience and growth. Specific client examples like the airport operator help illustrate the benefits. However, the link to Sopra Steria's specific offerings and approach could be more explicit."
        },
        "trust_&_credibility_signals": {
          "score": 8,
          "rationale": "The post features authoritative quotes from multiple Sopra Steria subject matter experts, lending credibility. Client examples and data points from Gartner research further enhance trust. Linking to more detailed case studies or white papers could provide even stronger proof points."
        },
        "call-to-action_effectiveness": {
          "score": 6,
          "rationale": "While the post makes a compelling case for supply chain ecosystems, the call-to-action for the target CXO persona is unclear. There are no explicit next steps like contacting Sopra Steria for an ecosystem assessment or linking to relevant services pages. Clearer CTAs would improve lead generation and engagement."
        }
      },
      "recommendations": []
    },
    "experience_report": {
      "overall_sentiment": "Neutral",
      "engagement_level": "Low",
      "conversion_likelihood": "Low",
      "effective_copy": [],
      "ineffective_copy": [],
      "first_impression": "",
      "strategic_analysis": ""
    },
    "embeddings_content": {
      "combined_analysis": "HYGIENE SCORECARD:\n# Brand Hygiene Scorecard\n\n**URL:** https://www.soprasteria.nl/newsroom/blog/details/ecosystems-yes-please-but-how-can-we-trust-each-other\n**Persona:** Unknown Persona (This persona encompasses Chief Technology Officers (CTOs), Chief Digital Officers (CDOs), and their C-suite peers, such as Chief Information Officers (CIOs). They are typically strategic business leaders responsible for driving growth and transformation through technology.)\n**Audited:** 2025-06-21 16:02:29\n\n---\n\n## Overall Assessment\n\n- **Tier/Channel:** Thought Leadership Blog Post\n- **Final Score:** 7.4/10\n\n---\n\n## Detailed Scoring\n\n| Category | Score | Rationale |\n| -------- | ----- | --------- |\n| Corporate Positioning Alignment | 8 | The blog post aligns well with Sopra Steria's positioning as a digital transformation partner, discussing how to build resilient supply chain ecosystems through technology. It showcases their expertise in data platforms, cybersecurity, and industry knowledge. |\n| Brand Differentiation | 6 | While the content demonstrates Sopra Steria's capabilities, it lacks strong differentiation from competitors. The insights, while valuable, are relatively generic and could apply to many technology consulting firms. More unique Sopra Steria IP or methodologies would strengthen differentiation. |\n| Value Proposition Clarity | 7 | The post articulates a clear value proposition around building collaborative, data-driven supply chain ecosystems to drive efficiency, resilience and growth. Specific client examples like the airport operator help illustrate the benefits. However, the link to Sopra Steria's specific offerings and approach could be more explicit. |\n| Trust & Credibility Signals | 8 | The post features authoritative quotes from multiple Sopra Steria subject matter experts, lending credibility. Client examples and data points from Gartner research further enhance trust. Linking to more detailed case studies or white papers could provide even stronger proof points. |\n| Call-to-Action Effectiveness | 6 | While the post makes a compelling case for supply chain ecosystems, the call-to-action for the target CXO persona is unclear. There are no explicit next steps like contacting Sopra Steria for an ecosystem assessment or linking to relevant services pages. Clearer CTAs would improve lead generation and engagement. |\n\n---\n\n## Summary Rationale\n\nFor a CTO/CDO/CIO persona, this blog post provides a solid overview of the benefits and challenges of building collaborative supply chain ecosystems. It aligns with their priorities around using data, AI and digital platforms to drive transformation and business value. \n\nThe Sopra Steria experts provide credible insights on key CXO considerations like change management, data governance, cybersecurity and the role of regulations. Client examples help illustrate the concepts.\n\nHowever, to fully resonate with this persona, the post should tie the insights more directly to Sopra Steria's unique offerings and value proposition. Greater differentiation and a stronger CTA would help move CXO readers down the funnel from awareness to consideration and engagement.\n\n---\n\n## Priority Recommendations\n\n1. **Strengthen differentiation** - Highlight Sopra Steria's unique IP, methodologies or offerings related to building collaborative data ecosystems. What sets the firm apart?\n\n2. **Sharpen the CXO value proposition** - Make the benefits for CXOs even clearer by quantifying potential cost savings, revenue growth, market share or other KPIs they care about. Tie the supply chain ecosystem opportunity more directly to their digital transformation priorities.\n\n3. **Add clear CXO calls-to-action** - Include prominent CTAs for CXO-relevant next steps like signing up for an ecosystem assessment, workshop or consultation with Sopra Steria experts. Drive them to services pages, case studies or CXO-focused content to continue the journey.\n\nEXPERIENCE REPORT:\nError: Could not generate the experience report due to a persistent API error.",
      "key_themes": [
        "trust",
        "security",
        "compliance",
        "innovation",
        "risk"
      ],
      "business_impact": ""
    },
    "metadata": {
      "persona_id": "the_benelux_technology_innovation_leader",
      "page_id": "fe8eb8c2",
      "tier": "thought",
      "final_score": 7.4,
      "domain": "www.soprasteria.nl",
      "content_type": "blog",
      "regulatory_frameworks": [],
      "is_benelux": true,
      "has_compliance_content": true,
      "has_security_content": true,
      "compiled_at": "2025-07-03T07:43:07.394536"
    }
  },
  {
    "page_id": "58559e0e",
    "url": "https://www.soprasteria.be/",
    "slug": "wwwsoprasteriabe",
    "persona": {
      "name": "The_BENELUX_Technology_Innovation_Leader",
      "description": "Unknown Persona (This persona encompasses Chief Technology Officers (CTOs), Chief Digital Officers (CDOs), and their C-suite peers, such as Chief Information Officers (CIOs). They are typically strategic business leaders responsible for driving growth and transformation through technology.)"
    },
    "hygiene_scorecard": {
      "tier": "Corporate",
      "final_score": 7.2,
      "brand_health_index": 6.32,
      "trust_gap": 0.0,
      "audited_ts": "2025-06-21",
      "detailed_scores": {
        "|_corporate_positioning_alignment": {
          "score": 8,
          "rationale": "The page reflects Sopra Steria's core brand message of shaping the world through technology fairly well, with the tagline \"The world is how we shape it\" and content focused on digital transformation. However, the connection could be made even more explicit. Evidence: Tagline, section on \"What we do\"."
        },
        "value_proposition_clarity": {
          "score": 7,
          "rationale": "The page communicates a high-level value prop around empowering clients to excel through technology, but lacks specificity on how Sopra Steria delivers unique value for CTOs/CDOs. Evidence: \"We empower you to excel by streamlining processes, enhancing productivity, and driving innovation in a dynamic business environment.\""
        }
      },
      "recommendations": []
    },
    "experience_report": {
      "overall_sentiment": "Neutral",
      "engagement_level": "Low",
      "conversion_likelihood": "Low",
      "effective_copy": [
        {
          "text": "\"The Future of Generative AI: Insights and Strategies for 2025. Our latest report offers a detailed analysis of the GenAI landscape, combining insights from various sources and Sopra Steria's AI specialists. It highlights key trends, technological advancements, and strategic recommendations for 2025.\"",
          "analysis": "As a CTO/CDO, unlocking business value through AI is a top priority for me. This content demonstrates Sopra Steria's forward-looking expertise in this critical area and provides the type of strategic insights and recommendations that are valuable for shaping my technology roadmap. The 2025 focus aligns with my long-term planning horizon."
        },
        {
          "text": "\"DORA: A New Pillar of Digital Resilience. The importance of a unified, pragmatic approach to compliance\"",
          "analysis": "Balancing innovation with security and compliance is a constant challenge in my role. This content signals that Sopra Steria understands this pain point and can help me navigate complex regulatory landscapes like DORA in a practical way, which builds credibility."
        }
      ],
      "ineffective_copy": [
        {
          "text": "\"We empower you to excel by streamlining processes, enhancing productivity, and driving innovation in a dynamic business environment.\"",
          "analysis": "As a strategic technology leader, this high-level statement lacks the specificity and proof points I need to understand how Sopra Steria can tangibly support my key priorities around digital transformation and harnessing data/AI. The language is too generic to be impactful."
        },
        {
          "text": "\"Sopra Steria, a major Tech player in Europe with 50,000 employees in nearly 30 countries, is recognised for its consulting, digital services and solutions.\"",
          "analysis": "While the scale and geographic reach of Sopra Steria may be notable, as a C-suite technology leader this broad description does not give me a clear sense of their specific capabilities or track record of delivering business outcomes that are relevant to my priorities and challenges."
        }
      ],
      "first_impression": "",
      "strategic_analysis": ""
    },
    "embeddings_content": {
      "combined_analysis": "HYGIENE SCORECARD:\n# Brand Hygiene Scorecard\n\n**URL:** https://www.soprasteria.be/\n**Persona:** Unknown Persona (This persona encompasses Chief Technology Officers (CTOs), Chief Digital Officers (CDOs), and their C-suite peers, such as Chief Information Officers (CIOs). They are typically strategic business leaders responsible for driving growth and transformation through technology.)\n**Audited:** 2025-06-21 15:49:18\n\n---\n\n## Overall Assessment\n\n- **Tier/Channel:** Corporate Website - Top Level\n- **Final Score:** 7.2/10\n\n---\n\n## Detailed Scoring\n\n| Category | Score | Rationale |\n| -------- | ----- | --------- |\n| Corporate Positioning Alignment | 8 | The page reflects Sopra Steria's core brand message of shaping the world through technology fairly well, with the tagline \"The world is how we shape it\" and content focused on digital transformation. However, the connection could be made even more explicit. Evidence: Tagline, section on \"What we do\".\n| Brand Differentiation | 6 | While the page mentions Sopra Steria's scale and capabilities, it doesn't clearly articulate what makes them uniquely positioned compared to other major technology consultancies. The content is still somewhat generic. Evidence: Stats on number of employees, list of services.\n| Value Proposition Clarity | 7 | The page communicates a high-level value prop around empowering clients to excel through technology, but lacks specificity on how Sopra Steria delivers unique value for CTOs/CDOs. Evidence: \"We empower you to excel by streamlining processes, enhancing productivity, and driving innovation in a dynamic business environment.\"\n| Trust & Credibility Signals | 8 | Sopra Steria's scale, client stories, and thought leadership content lend credibility, but more proof points around successful CTO/CDO-level engagements would strengthen trust. Evidence: Employee count, offices, client stories, whitepapers.\n| Call-to-Action Effectiveness | 7 | CTAs for insights content are relevant for a CTO/CDO audience, but there is no clear next step for engaging Sopra Steria directly on CTO/CDO priorities like AI transformation. Evidence: Links to whitepapers, blogs, no contact/consultation CTA.\n\n---\n\n## Summary Rationale\n\nFor a CTO/CDO persona, the Sopra Steria homepage demonstrates good alignment with their general priorities around using technology to drive business transformation. The page conveys Sopra Steria's scale and breadth of capabilities, lending credibility. \n\nHowever, the page lacks clear differentiation vs. other major technology consultancies and doesn't speak directly enough to the CTO/CDO agenda. The value proposition and calls-to-action could be more tailored to resonate with CTO/CDO-specific needs around harnessing emerging technologies like AI to reinvent the business.\n\nOverall, the page is professional and builds trust, but has room to be more differentiated and impactful in engaging a CTO/CDO audience. Tailoring the messaging and next steps to their specific priorities would elevate relevance and response.\n\n---\n\n## Priority Recommendations\n\n1. **Sharpen CTO/CDO-Centric Messaging** - Evolve the value proposition and supporting points to speak more directly to CTO/CDO priorities like AI transformation, data-driven innovation, and balancing innovation with security/compliance. Make Sopra Steria's unique POV clearer.\n\n2. **Elevate Proof Points** - Integrate more examples, case studies or quotes that highlight successful CTO/CDO-level engagements and underscore Sopra Steria's ability to drive strategic impact for technology leaders. \n\n3. **Add CTO/CDO-Specific Calls-to-Action** - Include clearer next steps for CTOs/CDOs to engage Sopra Steria to discuss their transformation priorities, such as a consultation offer or relevant contact.\n\nEXPERIENCE REPORT:\n| Finding          | Example from Text | Strategic Analysis (from Persona's View)            |\n| ---------------- | ----------------- | --------------------------------------------------- |\n| Ineffective Copy | \"We empower you to excel by streamlining processes, enhancing productivity, and driving innovation in a dynamic business environment.\" | As a strategic technology leader, this high-level statement lacks the specificity and proof points I need to understand how Sopra Steria can tangibly support my key priorities around digital transformation and harnessing data/AI. The language is too generic to be impactful. |\n| Effective Copy   | \"The Future of Generative AI: Insights and Strategies for 2025. Our latest report offers a detailed analysis of the GenAI landscape, combining insights from various sources and Sopra Steria's AI specialists. It highlights key trends, technological advancements, and strategic recommendations for 2025.\"   | As a CTO/CDO, unlocking business value through AI is a top priority for me. This content demonstrates Sopra Steria's forward-looking expertise in this critical area and provides the type of strategic insights and recommendations that are valuable for shaping my technology roadmap. The 2025 focus aligns with my long-term planning horizon. |\n| Ineffective Copy | \"Sopra Steria, a major Tech player in Europe with 50,000 employees in nearly 30 countries, is recognised for its consulting, digital services and solutions.\" | While the scale and geographic reach of Sopra Steria may be notable, as a C-suite technology leader this broad description does not give me a clear sense of their specific capabilities or track record of delivering business outcomes that are relevant to my priorities and challenges. |\n| Effective Copy   | \"DORA: A New Pillar of Digital Resilience. The importance of a unified, pragmatic approach to compliance\" | Balancing innovation with security and compliance is a constant challenge in my role. This content signals that Sopra Steria understands this pain point and can help me navigate complex regulatory landscapes like DORA in a practical way, which builds credibility. |\n\nAs a CTO/CDO, my first impression of this Sopra Steria webpage is mixed. While there are some elements that resonate, such as the forward-looking content on Generative AI and the emphasis on digital resilience, overall the value proposition for a strategic technology leader like myself is not as crisp and compelling as it could be. The language in places is quite generic and high-level, lacking the specificity and proof points I would need to understand how Sopra Steria is uniquely positioned to help me drive transformation and business value through technology.\n\nIn terms of gaps, I would like to see more concrete examples and case studies demonstrating Sopra Steria's impact for organizations like mine - what measurable outcomes have they helped other clients achieve in areas like AI deployment, legacy modernization, and balancing innovation with security? The client stories are a good start but lack the quantitative metrics that really speak to business impact. I also don't get a strong sense of Sopra Steria's specific differentiators compared to other technology services firms I may be considering.\n\nThat said, content like the DORA compliance piece and the Generative AI report do help build credibility by demonstrating Sopra Steria's understanding of the strategic issues and evolving technology landscape that are top of mind for me. The geographic coverage across Benelux is also a plus given my scope. However, to fully gain my trust and move me to the next step of engagement, I would recommend Sopra Steria double down on showcasing their unique capabilities, proven delivery track record, and ability to drive tangible business outcomes that map to my KPIs as a C-suite leader. Sharper messaging, more hard-hitting proof points, and clearer calls-to-action for my persona would go a long way in strengthening the impact of this page.",
      "key_themes": [
        "trust",
        "security",
        "compliance",
        "innovation",
        "risk"
      ],
      "business_impact": ""
    },
    "metadata": {
      "persona_id": "the_benelux_technology_innovation_leader",
      "page_id": "58559e0e",
      "tier": "corporate",
      "final_score": 7.2,
      "domain": "www.soprasteria.be",
      "content_type": "unknown",
      "regulatory_frameworks": [],
      "is_benelux": true,
      "has_compliance_content": true,
      "has_security_content": true,
      "compiled_at": "2025-07-03T07:43:07.395348"
    }
  },
  {
    "page_id": "cded0b85",
    "url": "https://www.soprasteria.be/whatwedo/digital-themes/deliver-flexible-always-on-performance/cloud-infrastructure-platforms/sopra-steria-transformation-services-for-microsoft-azure",
    "slug": "wwwsoprasteriabewhatwedodigital-themesdeliver-flexible-always-on-performancecloud-infrastructure-platformssopra-steria-transformation-services-for-microsoft-azure",
    "persona": {
      "name": "The_BENELUX_Technology_Innovation_Leader",
      "description": "Unknown Persona (This persona encompasses Chief Technology Officers (CTOs), Chief Digital Officers (CDOs), and their C-suite peers, such as Chief Information Officers (CIOs). They are typically strategic business leaders responsible for driving growth and transformation through technology.)"
    },
    "hygiene_scorecard": {
      "tier": "Service",
      "final_score": 7.8,
      "brand_health_index": 6.68,
      "trust_gap": 0.2,
      "audited_ts": "2025-06-21",
      "detailed_scores": {
        "|_corporate_positioning_alignment": {
          "score": 8,
          "rationale": "The page aligns well with Sopra Steria's core brand message around digital transformation and leveraging technology like AI and cloud for business impact. Key phrases like \"In the age of AI-driven business, maximizing your digital investments and driving operational efficiency are essential\" reflect this. However, the messaging could be further elevated to emphasize Sopra Steria's unique approach."
        },
        "brand_differentiation": {
          "score": 7,
          "rationale": "The Microsoft partnership and specific services like the Azure Well-Architected Framework Review help differentiate Sopra Steria. Statistics on their Microsoft expertise add credibility. However, more could be done to highlight what truly sets Sopra Steria apart from other Azure service providers in a crowded market. Unique methodologies, IP, or client results would strengthen differentiation."
        },
        "value_proposition_clarity": {
          "score": 8,
          "rationale": "The page clearly articulates the value prop around empowering business processes and driving efficiency/growth with Azure. Specific benefits are called out like improving CX, revenue and productivity. The service offerings provide a comprehensive view of the value across migration, modernization, data/AI, managed services, security and sustainability."
        },
        "trust_&_credibility_signals": {
          "score": 8,
          "rationale": "Several proof points are included to build trust, such as the 18-year Microsoft partnership, 5500 skilled professionals, 700+ certifications, and Azure Expert MSP status. The 12 Microsoft specializations further validate their expertise. Client success stories add credibility, though more could be included, especially quantified results achieved."
        },
        "call-to-action_effectiveness": {
          "score": 8,
          "rationale": "The main CTA to \"Let's Talk\" and contact Sopra Steria is prominent and clear for a C-level audience looking to discuss Azure opportunities. Reiterating this CTA in the closing section with a tie back to the value prop is effective. The secondary CTA to read related blog content is also relevant to engage a C-level audience further in their journey."
        }
      },
      "recommendations": []
    },
    "experience_report": {
      "overall_sentiment": "Neutral",
      "engagement_level": "Low",
      "conversion_likelihood": "Low",
      "effective_copy": [
        {
          "text": "\"We identify risks and provide actionable recommendations to optimize your Azure domains, platforms, and workloads for peak performance.\"",
          "analysis": "As a CTO/CDO, I appreciate the focus on risk identification and actionable recommendations. Optimizing our Azure environment for performance is a key priority and pain point for me. This shows an understanding of my needs."
        },
        {
          "text": "\"Expertly managed services to run complex applications using automation, AIOps, DevSecOps, and Site Reliability Engineering (SRE). Our moder cloud practices ensure seamless, efficient operations on Azure.\"",
          "analysis": "As someone responsible for balancing innovation with security and efficiency, I'm encouraged by the mention of modern practices like AIOps, DevSecOps and SRE to manage complex apps on Azure. This aligns well with my priorities."
        }
      ],
      "ineffective_copy": [
        {
          "text": "\"Sopra Steria migration, modernisation and Cloud-native apps development A value-led, flexible, and cost-effective path to accelerate your cloud adoption.\"",
          "analysis": "As a strategic Technology & Innovation Leader, this high-level statement lacks the specificity and tangible business outcomes I need to justify investment. It's too generic to be compelling."
        },
        {
          "text": "\"Enhance business functions like sales, customer service, and finance with Microsoft Dynamics 365 Copilot.\"",
          "analysis": "As a C-suite technology leader, I need more than just a list of business functions. What are the measurable efficiency gains and ROI I can expect? How will this integrate with my existing systems? The value prop is too vague."
        }
      ],
      "first_impression": "",
      "strategic_analysis": ""
    },
    "embeddings_content": {
      "combined_analysis": "HYGIENE SCORECARD:\n# Brand Hygiene Scorecard\n\n**URL:** https://www.soprasteria.be/whatwedo/digital-themes/deliver-flexible-always-on-performance/cloud-infrastructure-platforms/sopra-steria-transformation-services-for-microsoft-azure\n**Persona:** Unknown Persona (This persona encompasses Chief Technology Officers (CTOs), Chief Digital Officers (CDOs), and their C-suite peers, such as Chief Information Officers (CIOs). They are typically strategic business leaders responsible for driving growth and transformation through technology.)\n**Audited:** 2025-06-21 15:54:47\n\n---\n\n## Overall Assessment\n\n- **Tier/Channel:** Service Offering Page \n- **Final Score:** 7.8/10\n\n---\n\n## Detailed Scoring\n\n| Category | Score | Rationale |\n| -------- | ----- | --------- |\n| Corporate Positioning Alignment | 8 | The page aligns well with Sopra Steria's core brand message around digital transformation and leveraging technology like AI and cloud for business impact. Key phrases like \"In the age of AI-driven business, maximizing your digital investments and driving operational efficiency are essential\" reflect this. However, the messaging could be further elevated to emphasize Sopra Steria's unique approach. |\n| Brand Differentiation | 7 | The Microsoft partnership and specific services like the Azure Well-Architected Framework Review help differentiate Sopra Steria. Statistics on their Microsoft expertise add credibility. However, more could be done to highlight what truly sets Sopra Steria apart from other Azure service providers in a crowded market. Unique methodologies, IP, or client results would strengthen differentiation. |\n| Value Proposition Clarity | 8 | The page clearly articulates the value prop around empowering business processes and driving efficiency/growth with Azure. Specific benefits are called out like improving CX, revenue and productivity. The service offerings provide a comprehensive view of the value across migration, modernization, data/AI, managed services, security and sustainability. |\n| Trust & Credibility Signals | 8 | Several proof points are included to build trust, such as the 18-year Microsoft partnership, 5500 skilled professionals, 700+ certifications, and Azure Expert MSP status. The 12 Microsoft specializations further validate their expertise. Client success stories add credibility, though more could be included, especially quantified results achieved. |\n| Call-to-Action Effectiveness | 8 | The main CTA to \"Let's Talk\" and contact Sopra Steria is prominent and clear for a C-level audience looking to discuss Azure opportunities. Reiterating this CTA in the closing section with a tie back to the value prop is effective. The secondary CTA to read related blog content is also relevant to engage a C-level audience further in their journey. |\n\n---\n\n## Summary Rationale\n\nFor a C-level technology leader looking to drive digital transformation and business impact with Azure, this page from Sopra Steria provides a strong overview of relevant service offerings and expertise. The messaging aligns with key priorities around maximizing digital investments, driving efficiency, and harnessing data/AI. \n\nSopra Steria's credibility as an Azure partner is well-established through proof points like certifications and specializations. Client success stories and a clear CTA to engage further help move C-level buyers along the journey.\n\nThe main area for improvement is strengthening Sopra Steria's unique differentiation in the crowded Azure services market. Highlighting proprietary methodologies, tools, or standout client results would help them rise above competitors. \n\nOverall, this page is well-targeted to C-level technology leaders and makes a compelling case for Sopra Steria as a trusted Azure transformation partner. With sharper differentiation, it could be even more impactful in persuading this audience.\n\n---\n\n## Priority Recommendations\n\n1. **Sharpen Sopra Steria's unique differentiation** - Highlight proprietary methodologies, tools, IP or standout client results that showcase how Sopra Steria's Azure services are uniquely beneficial compared to competitors.\n\n2. **Add more client proof points** - Include additional client success stories, especially with quantified business impact achieved, to further validate Sopra Steria's Azure capabilities in the eyes of C-level buyers.\n\n3. **Elevate the Sopra Steria value prop** - While the page explains the value of Azure services well, enhance messaging around Sopra Steria's unique value prop and approach to make their offering even more compelling to C-level leaders.\n\nEXPERIENCE REPORT:\n| Finding          | Example from Text | Strategic Analysis (from Persona's View)            |\n| ---------------- | ----------------- | --------------------------------------------------- |\n| Ineffective Copy | \"Sopra Steria migration, modernisation and Cloud-native apps development A value-led, flexible, and cost-effective path to accelerate your cloud adoption.\" | As a strategic Technology & Innovation Leader, this high-level statement lacks the specificity and tangible business outcomes I need to justify investment. It's too generic to be compelling. |\n| Effective Copy   | \"We identify risks and provide actionable recommendations to optimize your Azure domains, platforms, and workloads for peak performance.\"  | As a CTO/CDO, I appreciate the focus on risk identification and actionable recommendations. Optimizing our Azure environment for performance is a key priority and pain point for me. This shows an understanding of my needs. |\n| Ineffective Copy | \"Enhance business functions like sales, customer service, and finance with Microsoft Dynamics 365 Copilot.\" | As a C-suite technology leader, I need more than just a list of business functions. What are the measurable efficiency gains and ROI I can expect? How will this integrate with my existing systems? The value prop is too vague. |\n| Effective Copy   | \"Expertly managed services to run complex applications using automation, AIOps, DevSecOps, and Site Reliability Engineering (SRE). Our moder cloud practices ensure seamless, efficient operations on Azure.\" | As someone responsible for balancing innovation with security and efficiency, I'm encouraged by the mention of modern practices like AIOps, DevSecOps and SRE to manage complex apps on Azure. This aligns well with my priorities. |\n\nFirst-Person Narrative Analysis:\n\nAs a CTO/CDO responsible for driving digital transformation and growth, my first impression of this Sopra Steria webpage is mixed. While some elements speak directly to my priorities around optimizing Azure performance, harnessing data and AI, and balancing innovation with security, other sections come across as too generic and high-level to be truly compelling. \n\nThe language is hit or miss in resonating with my C-suite perspective. Mentions of \"actionable recommendations\", \"modern cloud practices\", and comprehensive data/AI services are promising. However, there are notable gaps in information that I would need to move forward - namely, more tangible proof points around business outcomes, efficiency gains, and ROI. As someone tasked with demonstrating business value, I don't just need to know that Sopra Steria offers migration and modernization services, but how those will measurably impact my KPIs and bottom line.\n\nIn terms of building trust and credibility, the page does get some things right. Calling out their 18-year Microsoft partnership, skilled talent pool, and expert MSP status lends legitimacy. I'm also encouraged by the emphasis on AI-powered security and compliance, which are make-or-break issues for any technology leader today. That said, the page would benefit from more client success stories and hard metrics that back up their claims.\n\nIf I'm candid, I don't feel this page alone would spur me to take immediate action. To improve its impact on strategic decision-makers like myself, I'd recommend:\n1) Framing the services in terms of overcoming my specific pain points and achieving my business KPIs \n2) Providing more concrete proof points, client results and differentiators to establish credibility\n3) Clarifying how their offerings can be tailored to my industry and integrate with my existing environment\n4) Highlighting more C-suite-relevant content around digital transformation strategy and maximizing my Azure ROI\n\nWith some refinement to better align with my perspective, this page could more effectively drive engagement with Technology & Innovation Leaders.",
      "key_themes": [
        "trust",
        "security",
        "compliance",
        "innovation",
        "risk"
      ],
      "business_impact": ""
    },
    "metadata": {
      "persona_id": "the_benelux_technology_innovation_leader",
      "page_id": "cded0b85",
      "tier": "service",
      "final_score": 7.8,
      "domain": "www.soprasteria.be",
      "content_type": "service",
      "regulatory_frameworks": [],
      "is_benelux": true,
      "has_compliance_content": true,
      "has_security_content": true,
      "compiled_at": "2025-07-03T07:43:07.396479"
    }
  },
  {
    "page_id": "51dceb19",
    "url": "https://www.soprasteria.com/about-us/history",
    "slug": "wwwsoprasteriacomabout-ushistory",
    "persona": {
      "name": "The_BENELUX_Technology_Innovation_Leader",
      "description": "Unknown Persona (This persona encompasses Chief Technology Officers (CTOs), Chief Digital Officers (CDOs), and their C-suite peers, such as Chief Information Officers (CIOs). They are typically strategic business leaders responsible for driving growth and transformation through technology.)"
    },
    "hygiene_scorecard": {
      "tier": "About",
      "final_score": 6.4,
      "brand_health_index": 5.84,
      "trust_gap": 0.3,
      "audited_ts": "2025-06-21",
      "detailed_scores": {
        "|_corporate_positioning_alignment": {
          "score": 7,
          "rationale": "The page reflects Sopra Steria's focus on digital transformation and supporting clients' business needs. However, it lacks a clear articulation of the company's core brand message and mission. Evidence: \"For us, digital is first and foremost a human adventure.\""
        },
        "brand_differentiation": {
          "score": 5,
          "rationale": "The content provides an overview of Sopra Steria's history and acquisitions, but does not clearly differentiate the company from competitors. It lacks emphasis on unique selling points that would resonate with the CTO/CDO persona."
        },
        "value_proposition_clarity": {
          "score": 6,
          "rationale": "While the page mentions Sopra Steria's end-to-end solutions and ability to address core business needs, the value proposition for the CTO/CDO persona is not explicitly stated. More emphasis on how Sopra Steria enables digital transformation and drives business value through technology is needed."
        },
        "trust_&_credibility_signals": {
          "score": 7,
          "rationale": "The page highlights Sopra Steria's history, acquisitions, and ranking among top European digital transformation players, providing some credibility. However, it lacks specific proof points, case studies, or client testimonials that would build trust with the CTO/CDO persona."
        },
        "call-to-action_effectiveness": {
          "score": 5,
          "rationale": "There is no clear call-to-action or next step for the CTO/CDO persona on this page. The \"Learn more\" link under \"Our Commitments\" is not directly relevant to this persona's needs. A targeted CTA, such as \"Explore our digital transformation solutions\" or \"Contact us to discuss your technology strategy\" would be more effective."
        }
      },
      "recommendations": []
    },
    "experience_report": {
      "overall_sentiment": "Neutral",
      "engagement_level": "High",
      "conversion_likelihood": "High",
      "effective_copy": [
        {
          "text": "\"Today, the Group ranks among the top 5 European digital transformation players, having earned a reputation for providing end-to-end solutions to address the core business needs of large companies and organisations, helping them remain competitive and grow.\"",
          "analysis": "As a CTO/CDO, Sopra Steria's position as a top 5 player and track record with large enterprises catches my attention. The focus on end-to-end solutions to drive competitiveness and growth aligns well with my own objectives. I'd be interested to learn more about the specific solutions and outcomes they've delivered in this space."
        },
        {
          "text": "\"With the acquisition of Sodifrance in 2020, the Group becomes a leader in digital services for insurance and welfare protection.\"",
          "analysis": "Given my role in driving transformation, Sopra Steria's targeted acquisition to establish leadership in the insurance vertical shows a level of industry focus and expertise that resonates with me. As a technology decision maker, I look for partners that deeply understand my business context and can tailor solutions accordingly. This helps build their credibility."
        }
      ],
      "ineffective_copy": [
        {
          "text": "\"For us, digital is first and foremost a human adventure.\"",
          "analysis": "As a CTO/CDO focused on driving business value through technology, this statement comes across as vague and lacking substance. I need to understand how Sopra Steria's approach translates into tangible outcomes and ROI for my organization. Humanizing digital is nice, but how does it solve my key challenges?"
        },
        {
          "text": "\"The Sopra Steria 2020 Project is launched to improve the Group's performance in all areas and increase its added value.\"",
          "analysis": "From my perspective as a technology leader, this provides no insight into how Sopra Steria can help me achieve my strategic priorities. It's an inward-facing statement about their own initiative without any connection to the value it delivers to clients like me. I need to know what specific capabilities and solutions they bring to the table."
        }
      ],
      "first_impression": "",
      "strategic_analysis": ""
    },
    "embeddings_content": {
      "combined_analysis": "HYGIENE SCORECARD:\n# Brand Hygiene Scorecard\n\n**URL:** https://www.soprasteria.com/about-us/history\n**Persona:** Unknown Persona (This persona encompasses Chief Technology Officers (CTOs), Chief Digital Officers (CDOs), and their C-suite peers, such as Chief Information Officers (CIOs). They are typically strategic business leaders responsible for driving growth and transformation through technology.)\n**Audited:** 2025-06-21 15:52:26\n\n---\n\n## Overall Assessment\n\n- **Tier/Channel:** About Us - History Page\n- **Final Score:** 6.4/10\n\n---\n\n## Detailed Scoring\n\n| Category | Score | Rationale |\n| -------- | ----- | --------- |\n| Corporate Positioning Alignment | 7 | The page reflects Sopra Steria's focus on digital transformation and supporting clients' business needs. However, it lacks a clear articulation of the company's core brand message and mission. Evidence: \"For us, digital is first and foremost a human adventure.\" |\n| Brand Differentiation | 5 | The content provides an overview of Sopra Steria's history and acquisitions, but does not clearly differentiate the company from competitors. It lacks emphasis on unique selling points that would resonate with the CTO/CDO persona. |\n| Value Proposition Clarity | 6 | While the page mentions Sopra Steria's end-to-end solutions and ability to address core business needs, the value proposition for the CTO/CDO persona is not explicitly stated. More emphasis on how Sopra Steria enables digital transformation and drives business value through technology is needed. |\n| Trust & Credibility Signals | 7 | The page highlights Sopra Steria's history, acquisitions, and ranking among top European digital transformation players, providing some credibility. However, it lacks specific proof points, case studies, or client testimonials that would build trust with the CTO/CDO persona. |\n| Call-to-Action Effectiveness | 5 | There is no clear call-to-action or next step for the CTO/CDO persona on this page. The \"Learn more\" link under \"Our Commitments\" is not directly relevant to this persona's needs. A targeted CTA, such as \"Explore our digital transformation solutions\" or \"Contact us to discuss your technology strategy\" would be more effective. |\n\n---\n\n## Summary Rationale\n\nFrom the perspective of a CTO, CDO, or C-suite technology leader, the Sopra Steria history page provides a high-level overview of the company's journey and focus on digital transformation. However, it lacks a strong value proposition and differentiation that would compel this persona to engage further. \n\nThe page highlights Sopra Steria's acquisitions and growth, but does not clearly articulate how this benefits clients or enables them to achieve their digital transformation goals. The content is more internally focused, rather than addressing the specific challenges and priorities of technology leaders.\n\nTo improve the page's effectiveness for this persona, Sopra Steria should emphasize its unique capabilities, proven track record, and client success stories in driving digital transformation and business value through technology. Providing specific examples, case studies, or thought leadership content that demonstrates Sopra Steria's expertise in areas such as AI, data, and innovative business models would help build credibility and trust.\n\nAdditionally, including a clear and relevant call-to-action, such as an invitation to explore Sopra Steria's digital transformation solutions or connect with an expert, would guide the CTO/CDO persona towards the next step in engaging with the company.\n\n---\n\n## Priority Recommendations\n\n1. **Value Proposition** - Clearly articulate Sopra Steria's value proposition for technology leaders, emphasizing how the company's capabilities and experience enable digital transformation and drive business outcomes.\n\n2. **Differentiation** - Highlight Sopra Steria's unique strengths, innovative solutions, and proven track record in supporting clients' digital transformation journeys to differentiate from competitors.\n\n3. **Persona-Relevant Content** - Include specific examples, case studies, or thought leadership content that addresses the key challenges and priorities of CTOs, CDOs, and technology leaders, such as leveraging AI and data to create business value.\n\nEXPERIENCE REPORT:\n| Finding          | Example from Text | Strategic Analysis (from Persona's View)            |\n| ---------------- | ----------------- | --------------------------------------------------- |\n| Ineffective Copy | \"For us, digital is first and foremost a human adventure.\"  | As a CTO/CDO focused on driving business value through technology, this statement comes across as vague and lacking substance. I need to understand how Sopra Steria's approach translates into tangible outcomes and ROI for my organization. Humanizing digital is nice, but how does it solve my key challenges?  |\n| Ineffective Copy | \"The Sopra Steria 2020 Project is launched to improve the Group's performance in all areas and increase its added value.\" | From my perspective as a technology leader, this provides no insight into how Sopra Steria can help me achieve my strategic priorities. It's an inward-facing statement about their own initiative without any connection to the value it delivers to clients like me. I need to know what specific capabilities and solutions they bring to the table.  |\n| Effective Copy   | \"Today, the Group ranks among the top 5 European digital transformation players, having earned a reputation for providing end-to-end solutions to address the core business needs of large companies and organisations, helping them remain competitive and grow.\"   | As a CTO/CDO, Sopra Steria's position as a top 5 player and track record with large enterprises catches my attention. The focus on end-to-end solutions to drive competitiveness and growth aligns well with my own objectives. I'd be interested to learn more about the specific solutions and outcomes they've delivered in this space.  |\n| Effective Copy   | \"With the acquisition of Sodifrance in 2020, the Group becomes a leader in digital services for insurance and welfare protection.\" | Given my role in driving transformation, Sopra Steria's targeted acquisition to establish leadership in the insurance vertical shows a level of industry focus and expertise that resonates with me. As a technology decision maker, I look for partners that deeply understand my business context and can tailor solutions accordingly. This helps build their credibility. |\n\nFirst Impression:\nAs a CTO/CDO tasked with driving growth and transformation through technology, my initial impression of this Sopra Steria history page is mixed. While there are some elements that pique my interest, such as their positioning as a top European player and targeted industry acquisitions, much of the content feels too high-level and inward-facing. I don't get a clear sense of their unique value proposition and how they are equipped to help me address my key priorities and pain points. The page seems more focused on recounting Sopra Steria's own journey rather than articulating the business impact they deliver to technology leaders like myself.\n\nLanguage & Tone: \nThe language on this page doesn't fully resonate with me as a CTO/CDO. Statements like \"digital is first and foremost a human adventure\" come across as lofty platitudes without substance behind them. As a technology decision maker grappling with legacy systems, budget constraints, and pressure to harness data and AI, I need specifics on how Sopra Steria can help me overcome these hurdles. That said, mentions of their end-to-end solutions, industry-specific acquisitions, and track record with large enterprises do align better with my perspective. To improve, the language should be less inward-facing and more directly tied to the outcomes and ROI I care about.\n\nGaps in Information:\nFrom my vantage point, there are some significant gaps in information on this page that hinder my ability to determine if Sopra Steria is the right partner. First and foremost, I don't see any concrete examples or case studies illustrating the business results they've helped other organizations like mine achieve. Measurable outcomes and ROI are critical proof points I need to see. Additionally, while the page mentions capabilities like AI and digital transformation at a high level, it lacks details on specific offerings, technologies, and methodologies that set Sopra Steria apart. As a technology leader, I need visibility into how they would tangibly execute on the initiatives that matter to me.\n\nTrust and Credibility:\nThis history page has a limited impact on building my trust and confidence in Sopra Steria's ability to drive value for my organization. While the longevity of the company and growth through acquisition demonstrate a level of stability, much of the information is too surface-level to establish deep credibility with a technology decision maker. I would need to see more substance behind the claims - client testimonials, quantified results, analyst recognition, solution details, etc. The industry-specific moves, like the Sodifrance acquisition for insurance, are a step in the right direction in showing they understand my world. But overall, this page on its own doesn't quite provide the depth I need to fully trust their expertise.\n\nBusiness Impact & Next Steps:\nIf I'm being frank, the business impact of this history page is likely minimal for a CTO/CDO like myself. While it provides some useful context on Sopra Steria's background and evolution, it doesn't give me the information I need to make a confident decision or clearly understand the value they provide. To improve this page, I would recommend:\n\n1) Framing the content more around the key priorities and challenges of technology leaders, rather than an internal company view. Speak directly to how you help us succeed.\n\n2) Providing more specifics and proof points around your capabilities, solutions, methodologies, and client results. I need to concretely grasp what differentiates you.\n\n3) Including direct quotes and case studies from CTO/CDO clients you've partnered with. Hearing from peers about the impact you've driven is hugely validating.\n\n4) Highlighting relevant analyst recognition, awards, and IP that demonstrate your expertise and leadership in areas that matter to technology decision makers.\n\n5) Offering a clear next step or call-to-action for someone in my shoes to easily learn more or connect with your team. Make the path forward frictionless.\n\nBy incorporating these elements, the page would shift from a company-centric history lesson to a more powerful, persona-specific value proposition. That's what will capture the attention and interest of a technology leader like me.",
      "key_themes": [
        "trust",
        "security",
        "innovation"
      ],
      "business_impact": ""
    },
    "metadata": {
      "persona_id": "the_benelux_technology_innovation_leader",
      "page_id": "51dceb19",
      "tier": "about",
      "final_score": 6.4,
      "domain": "www.soprasteria.com",
      "content_type": "corporate",
      "regulatory_frameworks": [],
      "is_benelux": false,
      "has_compliance_content": false,
      "has_security_content": true,
      "compiled_at": "2025-07-03T07:43:07.397936"
    }
  },
  {
    "page_id": "97b9dedf",
    "url": "https://www.soprasteria.com/",
    "slug": "wwwsoprasteriacom",
    "persona": {
      "name": "The_BENELUX_Technology_Innovation_Leader",
      "description": "Unknown Persona (This persona encompasses Chief Technology Officers (CTOs), Chief Digital Officers (CDOs), and their C-suite peers, such as Chief Information Officers (CIOs). They are typically strategic business leaders responsible for driving growth and transformation through technology.)"
    },
    "hygiene_scorecard": {
      "tier": "Corporate",
      "final_score": 7.4,
      "brand_health_index": 6.44,
      "trust_gap": 0.2,
      "audited_ts": "2025-06-21",
      "detailed_scores": {
        "|_corporate_positioning_alignment": {
          "score": 8,
          "rationale": "The page reflects Sopra Steria's position as a major European tech player focused on consulting, digital services and solutions. Key messages around shaping technology, driving progress through digital, and combining tech with a human dimension align well with the brand. However, the core brand message could be articulated more succinctly upfront."
        },
        "brand_differentiation": {
          "score": 6,
          "rationale": "While the page mentions Sopra Steria's scale (50,000 employees across 30 countries) as a differentiator, there is limited content on what specifically sets them apart from other major tech services firms. The persona would likely want to see more on Sopra Steria's unique capabilities, approach, or track record of delivering business outcomes."
        },
        "value_proposition_clarity": {
          "score": 7,
          "rationale": "The value proposition around digital being a \"source of opportunities and progress for all\" and creating a \"virtuous circle benefiting society\" comes through but is quite high-level for a CTO/CDO persona. More specifics on how Sopra Steria enables enterprises to harness emerging technologies to drive transformation and business value would strengthen the proposition."
        },
        "trust_&_credibility_signals": {
          "score": 8,
          "rationale": "Sopra Steria's scale, geographic reach, and long-standing client relationships (e.g. Paris Air Show participation) provide solid credibility indicators for enterprise buyers. Highlighting specific client success stories, analyst recognition (e.g. the \"Open Innovation Report 2025\" feature), and unique capabilities would further boost trust."
        },
        "call-to-action_effectiveness": {
          "score": 7,
          "rationale": "The key calls-to-action (CTAs) to explore careers, manage cookies, read financial reports, or \"shape the world\" are somewhat buried and not optimally aligned to a CTO/CDO persona's top-of-funnel needs. Adding CTAs around exploring Sopra Steria's specific enterprise offerings, accessing relevant thought leadership, or connecting with industry experts would drive better engagement."
        }
      },
      "recommendations": []
    },
    "experience_report": {
      "overall_sentiment": "Neutral",
      "engagement_level": "Low",
      "conversion_likelihood": "Low",
      "effective_copy": [
        {
          "text": "\"Will your company survive the AI revolution? For future success businesses need to stop talking about AI and instead understand and integrate it into their operations.\"",
          "analysis": "As a CTO/CDO, harnessing AI to drive business value is a top priority for me. This headline grabs my attention by framing AI as an existential issue and implying Sopra Steria has a perspective on operationalizing AI vs. just talking about it. That aligns well with my goals."
        },
        {
          "text": "\"7 in 10 European companies judge startup collaboration as \"vital\" to their AI strategy, reveals a Sopra Steria report\"",
          "analysis": "As a technology leader exploring AI innovation, hard data on peer companies' AI strategies, especially regarding startup partnerships, provides valuable context for my decisions. Referencing this Sopra Steria research builds credibility that they understand the AI landscape and my challenges."
        }
      ],
      "ineffective_copy": [
        {
          "text": "\"Shaping Technology across Europe\"",
          "analysis": "As a C-suite technology leader focused on driving business value through AI and digital transformation, this tagline feels generic and lacks a clear tie-in to my strategic priorities. It doesn't convey how Sopra Steria can tangibly help me achieve \"Confident Momentum\" in my role."
        },
        {
          "text": "\"Welcome to our Corporate website\"",
          "analysis": "As an executive decision maker, I'm looking for substantive information relevant to my challenges, not a generic welcome message. This doesn't inspire confidence that the content will be tailored to my needs."
        }
      ],
      "first_impression": "",
      "strategic_analysis": ""
    },
    "embeddings_content": {
      "combined_analysis": "HYGIENE SCORECARD:\n# Brand Hygiene Scorecard\n\n**URL:** https://www.soprasteria.com/\n**Persona:** Unknown Persona (This persona encompasses Chief Technology Officers (CTOs), Chief Digital Officers (CDOs), and their C-suite peers, such as Chief Information Officers (CIOs). They are typically strategic business leaders responsible for driving growth and transformation through technology.)\n**Audited:** 2025-06-21 15:50:20\n\n---\n\n## Overall Assessment\n\n- **Tier/Channel:** Corporate Website - Home Page \n- **Final Score:** 7.4/10\n\n---\n\n## Detailed Scoring\n\n| Category | Score | Rationale |\n| -------- | ----- | --------- |\n| Corporate Positioning Alignment | 8 | The page reflects Sopra Steria's position as a major European tech player focused on consulting, digital services and solutions. Key messages around shaping technology, driving progress through digital, and combining tech with a human dimension align well with the brand. However, the core brand message could be articulated more succinctly upfront. |\n| Brand Differentiation | 6 | While the page mentions Sopra Steria's scale (50,000 employees across 30 countries) as a differentiator, there is limited content on what specifically sets them apart from other major tech services firms. The persona would likely want to see more on Sopra Steria's unique capabilities, approach, or track record of delivering business outcomes. |\n| Value Proposition Clarity | 7 | The value proposition around digital being a \"source of opportunities and progress for all\" and creating a \"virtuous circle benefiting society\" comes through but is quite high-level for a CTO/CDO persona. More specifics on how Sopra Steria enables enterprises to harness emerging technologies to drive transformation and business value would strengthen the proposition. |\n| Trust & Credibility Signals | 8 | Sopra Steria's scale, geographic reach, and long-standing client relationships (e.g. Paris Air Show participation) provide solid credibility indicators for enterprise buyers. Highlighting specific client success stories, analyst recognition (e.g. the \"Open Innovation Report 2025\" feature), and unique capabilities would further boost trust. |\n| Call-to-Action Effectiveness | 7 | The key calls-to-action (CTAs) to explore careers, manage cookies, read financial reports, or \"shape the world\" are somewhat buried and not optimally aligned to a CTO/CDO persona's top-of-funnel needs. Adding CTAs around exploring Sopra Steria's specific enterprise offerings, accessing relevant thought leadership, or connecting with industry experts would drive better engagement. |\n\n---\n\n## Summary Rationale\n\nFor a CTO/CDO persona, the Sopra Steria home page provides a solid introduction to the company's brand positioning and scale as a major European technology player. The emphasis on digital transformation, human-centric innovation, and societal progress aligns reasonably well with the persona's likely priorities. \n\nHowever, to drive deeper resonance and engagement, the page would benefit from more targeted and differentiated messaging around Sopra Steria's specific capabilities in areas like AI, data, cloud, cybersecurity, etc. Providing more proof points and success stories illustrating the tangible business outcomes Sopra Steria delivers for enterprise clients would further strengthen credibility.\n\nWhile the overall design and navigation is clean and professional, the page could be further optimized with more prominent, persona-relevant CTAs to explore offerings, access thought leadership, or connect with experts. Enhancing the enterprise value proposition and brand differentiation would help the page better stand out to technology decision-makers.\n\n---\n\n## Priority Recommendations\n\n1. **Strengthen value proposition for enterprise technology leaders** - Articulate a clearer, more specific value proposition around how Sopra Steria helps CTO/CDOs drive transformation and business outcomes. Emphasize unique capabilities in key areas like AI, data, cloud, cybersecurity.\n\n2. **Provide more targeted, differentiated messaging** - Enhance the page copy and proof points to better set Sopra Steria apart from other technology services firms. Highlight differentiating capabilities, approaches, frameworks, or client results that would resonate with a CTO/CDO persona.\n\n3. **Optimize CTAs for persona engagement** - Update the page CTAs to feature more persona-relevant \"next best actions\" such as exploring technology offerings, accessing thought leadership, viewing client success stories, or connecting with industry experts/account teams.\n\nEXPERIENCE REPORT:\n| Finding          | Example from Text | Strategic Analysis (from Persona's View)            |\n| ---------------- | ----------------- | --------------------------------------------------- |\n| Ineffective Copy | \"Shaping Technology across Europe\" | As a C-suite technology leader focused on driving business value through AI and digital transformation, this tagline feels generic and lacks a clear tie-in to my strategic priorities. It doesn't convey how Sopra Steria can tangibly help me achieve \"Confident Momentum\" in my role.  |\n| Ineffective Copy | \"Welcome to our Corporate website\" | As an executive decision maker, I'm looking for substantive information relevant to my challenges, not a generic welcome message. This doesn't inspire confidence that the content will be tailored to my needs. |\n| Effective Copy   | \"Will your company survive the AI revolution? For future success businesses need to stop talking about AI and instead understand and integrate it into their operations.\" | As a CTO/CDO, harnessing AI to drive business value is a top priority for me. This headline grabs my attention by framing AI as an existential issue and implying Sopra Steria has a perspective on operationalizing AI vs. just talking about it. That aligns well with my goals. |\n| Effective Copy | \"7 in 10 European companies judge startup collaboration as \"vital\" to their AI strategy, reveals a Sopra Steria report\" | As a technology leader exploring AI innovation, hard data on peer companies' AI strategies, especially regarding startup partnerships, provides valuable context for my decisions. Referencing this Sopra Steria research builds credibility that they understand the AI landscape and my challenges. |\n\nFirst-Person Analysis:\n\nMy initial impression of this Sopra Steria webpage is mixed. As a C-suite technology executive, I'm seeking partners who deeply understand my challenges around driving transformation and business value through AI and digitization. While there are some promising elements, like the AI revolution headline and startup collaboration data point, much of the page feels generic and untailored to my needs.\n\nThe page doesn't clearly convey Sopra Steria's differentiated value proposition for a technology leader like myself. Broad phrases like \"Shaping Technology across Europe\" and \"Welcome to our Corporate Website\" take up prominent real estate without communicating anything substantive about how they can help me achieve my strategic priorities. To build my confidence, I need to quickly grasp how their specific offerings map to my pain points around legacy modernization, talent gaps, and operationalizing AI. The \"Services\" menu suggests relevant capabilities, but the page doesn't connect the dots to my context.\n\nThere are some bright spots that pique my interest, notably the AI revolution provocation and the startup collaboration data. These signal that Sopra Steria has a point of view on key issues on my radar and is conducting relevant research. However, the page is missing critical information to help me determine fit, like case studies of similar clients, quantified business outcomes, and differentiators versus other providers. I'd also expect to see more emphasis on their BENELUX presence and experience, given my geographic focus.\n\nAs it stands, this page doesn't build strong trust and credibility with me as a BENELUX technology executive. The generic copy and lack of tailoring to my role make me question if Sopra Steria truly understands my world and goals. To improve, I'd recommend putting client proof points and provocative insights front and center, and ruthlessly eliminating generic fluff. Speak directly to personas like me using our language, lead with our priorities, and make a crystal-clear case for how you can accelerate our progress. Show, don't just tell, how you've helped similar leaders achieve \"Confident Momentum\" through AI and digital transformation.",
      "key_themes": [
        "trust",
        "security",
        "innovation"
      ],
      "business_impact": ""
    },
    "metadata": {
      "persona_id": "the_benelux_technology_innovation_leader",
      "page_id": "97b9dedf",
      "tier": "corporate",
      "final_score": 7.4,
      "domain": "www.soprasteria.com",
      "content_type": "unknown",
      "regulatory_frameworks": [],
      "is_benelux": false,
      "has_compliance_content": false,
      "has_security_content": true,
      "compiled_at": "2025-07-03T07:43:07.398709"
    }
  },
  {
    "page_id": "8fe8ea84",
    "url": "https://www.soprasteria.be/whatwedo/management-digital-transformation-consulting/services-operations-automation",
    "slug": "wwwsoprasteriabewhatwedomanagement-digital-transformation-consultingservices-operations-automation",
    "persona": {
      "name": "The_BENELUX_Technology_Innovation_Leader",
      "description": "Unknown Persona (This persona encompasses Chief Technology Officers (CTOs), Chief Digital Officers (CDOs), and their C-suite peers, such as Chief Information Officers (CIOs). They are typically strategic business leaders responsible for driving growth and transformation through technology.)"
    },
    "hygiene_scorecard": {
      "tier": "Services/Solutions",
      "final_score": 6.6,
      "brand_health_index": 5.96,
      "trust_gap": 0.5,
      "audited_ts": "2025-06-21",
      "detailed_scores": {
        "|_corporate_positioning_alignment": {
          "score": 7,
          "rationale": "The page aligns with Sopra Steria's focus on digital transformation and operational efficiency. However, it lacks a strong connection to the company's overarching brand message. Evidence: \"At Sopra Steria Next, our Services Operations & Automation practice is dedicated to helping organisations deliver on their customer promises.\""
        },
        "brand_differentiation": {
          "score": 6,
          "rationale": "While the page mentions some key service offerings like process optimization, RPA, and low-code solutions, it doesn't clearly articulate how Sopra Steria's approach is unique compared to competitors. More specifics are needed on their methodology and track record."
        },
        "value_proposition_clarity": {
          "score": 7,
          "rationale": "The page communicates the high-level benefits of improving operational efficiency and staying competitive. But it needs to provide more tangible examples of business outcomes and ROI that would resonate with C-level decision makers. Evidence: \"We're passionate about transforming your business. Our customised solutions drive efficiency, innovation, and excellence to ensure your business stays ahead of the competition.\""
        },
        "trust_&_credibility_signals": {
          "score": 5,
          "rationale": "The page is light on hard proof points like client logos, case studies, analyst recognition or team credentials that would build trust with senior executives. Linking to some of the success stories featured lower on the page could help."
        },
        "call-to-action_effectiveness": {
          "score": 8,
          "rationale": "The \"Let's Talk\" lead capture form is well-placed and the fields are relevant for this audience. Offering an option to download content like a whitepaper or benchmark report could provide additional hooks for engagement."
        }
      },
      "recommendations": []
    },
    "experience_report": {
      "overall_sentiment": "Neutral",
      "engagement_level": "Low",
      "conversion_likelihood": "Low",
      "effective_copy": [
        {
          "text": "\"With a team of over 50 consultants across Europe, we improve operational efficiency by optimising and automating business processes to ensure your operations run smoothly and effectively.\"",
          "analysis": "As a technology leader, this statement provides useful context about their team size and geographic scope. More importantly, it speaks directly to my goal of improving operational efficiency through process optimization and automation. This aligns well with my priorities."
        },
        {
          "text": "\"What we offer: Performance management, Process optimisation, Target operating model, Robotic process automation, Test automation, Hyper automation, Intelligent test automation, Pega Low-code solutions\"",
          "analysis": "As a technology decision-maker, I appreciate this concise list of their specific service offerings. Capabilities like RPA, test automation, and low-code platforms are highly relevant to my digital transformation goals. Seeing these competencies helps me gauge if they can address my needs."
        }
      ],
      "ineffective_copy": [
        {
          "text": "\"We're passionate about transforming your business. Our customised solutions drive efficiency, innovation, and excellence to ensure your business stays ahead of the competition.\"",
          "analysis": "As a CTO/CDO, this copy feels generic and lacks the specificity I need. What exact solutions do they offer and how do they tangibly drive efficiency and innovation? I need to see proof points and outcomes, not just vague promises."
        },
        {
          "text": "\"We're here to help you unlock the full potential of your operations and achieve remarkable results.\"",
          "analysis": "Again, as a C-suite technology executive, I find this language too vague and promotional. What defines the \"full potential\" of my operations and what constitutes \"remarkable results\"? I need tangible examples and KPIs, not fluff."
        }
      ],
      "first_impression": "",
      "strategic_analysis": ""
    },
    "embeddings_content": {
      "combined_analysis": "HYGIENE SCORECARD:\n# Brand Hygiene Scorecard\n\n**URL:** https://www.soprasteria.be/whatwedo/management-digital-transformation-consulting/services-operations-automation\n**Persona:** Unknown Persona (This persona encompasses Chief Technology Officers (CTOs), Chief Digital Officers (CDOs), and their C-suite peers, such as Chief Information Officers (CIOs). They are typically strategic business leaders responsible for driving growth and transformation through technology.)\n**Audited:** 2025-06-21 15:55:57\n\n---\n\n## Overall Assessment\n\n- **Tier/Channel:** Services/Solutions Page\n- **Final Score:** 6.6/10\n\n---\n\n## Detailed Scoring\n\n| Category | Score | Rationale |\n| -------- | ----- | --------- |\n| Corporate Positioning Alignment | 7 | The page aligns with Sopra Steria's focus on digital transformation and operational efficiency. However, it lacks a strong connection to the company's overarching brand message. Evidence: \"At Sopra Steria Next, our Services Operations & Automation practice is dedicated to helping organisations deliver on their customer promises.\" |\n| Brand Differentiation | 6 | While the page mentions some key service offerings like process optimization, RPA, and low-code solutions, it doesn't clearly articulate how Sopra Steria's approach is unique compared to competitors. More specifics are needed on their methodology and track record. |\n| Value Proposition Clarity | 7 | The page communicates the high-level benefits of improving operational efficiency and staying competitive. But it needs to provide more tangible examples of business outcomes and ROI that would resonate with C-level decision makers. Evidence: \"We're passionate about transforming your business. Our customised solutions drive efficiency, innovation, and excellence to ensure your business stays ahead of the competition.\" |\n| Trust & Credibility Signals | 5 | The page is light on hard proof points like client logos, case studies, analyst recognition or team credentials that would build trust with senior executives. Linking to some of the success stories featured lower on the page could help. |\n| Call-to-Action Effectiveness | 8 | The \"Let's Talk\" lead capture form is well-placed and the fields are relevant for this audience. Offering an option to download content like a whitepaper or benchmark report could provide additional hooks for engagement. |\n\n---\n\n## Summary Rationale\n\nFor a C-level technology leader evaluating potential transformation partners, this Services Operations & Automation page from Sopra Steria provides a solid overview of relevant capabilities but lacks the differentiation and credibility validators to be truly compelling. \n\nThe page communicates the importance of operational efficiency and business agility, which aligns with key priorities for this persona. Specific service offerings around process optimization, automation and low-code development are on-target.\n\nHowever, to stand out from competitors, Sopra Steria needs to provide a clearer articulation of their unique approach, supported by more tangible proof points. Client success stories, ROI examples, and team credentials would help build trust.\n\nWith some additional persona-relevant details and sharper differentiation, this page could more effectively engage and persuade C-suite technology decision makers.\n\n---\n\n## Priority Recommendations\n\n1. **Strengthen differentiation** - Clarify Sopra Steria's unique methodology, assets and track record in this space compared to alternatives.\n2. **Amplify trust signals** - Integrate client logos, case study excerpts, analyst quotes, and team credentials to validate capabilities.\n3. **Sharpen value proposition** - Provide more specific, quantified and persona-relevant examples of the business outcomes delivered.\n\nEXPERIENCE REPORT:\n| Finding          | Example from Text | Strategic Analysis (from Persona's View)            |\n| ---------------- | ----------------- | --------------------------------------------------- |\n| Ineffective Copy | \"We're passionate about transforming your business. Our customised solutions drive efficiency, innovation, and excellence to ensure your business stays ahead of the competition.\"      | As a CTO/CDO, this copy feels generic and lacks the specificity I need. What exact solutions do they offer and how do they tangibly drive efficiency and innovation? I need to see proof points and outcomes, not just vague promises. |\n| Effective Copy   | \"With a team of over 50 consultants across Europe, we improve operational efficiency by optimising and automating business processes to ensure your operations run smoothly and effectively.\"      | As a technology leader, this statement provides useful context about their team size and geographic scope. More importantly, it speaks directly to my goal of improving operational efficiency through process optimization and automation. This aligns well with my priorities.    |\n| Ineffective Copy | \"We're here to help you unlock the full potential of your operations and achieve remarkable results.\" | Again, as a C-suite technology executive, I find this language too vague and promotional. What defines the \"full potential\" of my operations and what constitutes \"remarkable results\"? I need tangible examples and KPIs, not fluff. |\n| Effective Copy | \"What we offer: Performance management, Process optimisation, Target operating model, Robotic process automation, Test automation, Hyper automation, Intelligent test automation, Pega Low-code solutions\" | As a technology decision-maker, I appreciate this concise list of their specific service offerings. Capabilities like RPA, test automation, and low-code platforms are highly relevant to my digital transformation goals. Seeing these competencies helps me gauge if they can address my needs.|\n\nAs a CTO/CDO responsible for driving digital transformation and innovation, my first impression of this Services Operations & Automation page is mixed. On one hand, I see some promising elements like their focus on process optimization, automation, and a Europe-wide presence. These align with my goals of improving operational efficiency and leveraging technology to transform the business. \n\nHowever, much of the copy feels generic and lacks the specificity I need to truly assess their capabilities. Statements about being \"passionate about transforming your business\" and delivering \"remarkable results\" sound good but don't give me a concrete sense of how they can help my organization. As a C-suite leader, I need to see hard proof points, tangible outcomes, and differentiating factors that are relevant to my industry and role.\n\nTo build more trust and credibility with someone in my position, I'd recommend providing more case studies or client examples that showcase the measurable business impact of their services. What efficiency gains, cost savings, or competitive advantages have they delivered for similar companies? The page mentions some key service offerings I care about like RPA, test automation, and low-code, but I'd like to see more detail on their approach, any unique IP/accelerators, and how they tie these capabilities to strategic business KPIs.\n\nOverall, while this page shows some potential alignment with my priorities, it doesn't quite give me the depth of information I need to feel fully confident in engaging with them. With some more role-specific messaging, supporting proof points, and ties to business outcomes, it could be a more effective tool in moving technology leaders like myself to the next stage. But as it stands, it leaves me with more questions than answers.",
      "key_themes": [
        "trust",
        "innovation"
      ],
      "business_impact": ""
    },
    "metadata": {
      "persona_id": "the_benelux_technology_innovation_leader",
      "page_id": "8fe8ea84",
      "tier": "services/solutions",
      "final_score": 6.6,
      "domain": "www.soprasteria.be",
      "content_type": "service",
      "regulatory_frameworks": [],
      "is_benelux": true,
      "has_compliance_content": false,
      "has_security_content": false,
      "compiled_at": "2025-07-03T07:43:07.399943"
    }
  },
  {
    "page_id": "b53c7bea",
    "url": "https://www.soprasteria.be/industries/industry-retail-logistics-telecom-media",
    "slug": "wwwsoprasteriabeindustriesindustry-retail-logistics-telecom-media",
    "persona": {
      "name": "The_BENELUX_Technology_Innovation_Leader",
      "description": "Unknown Persona (This persona encompasses Chief Technology Officers (CTOs), Chief Digital Officers (CDOs), and their C-suite peers, such as Chief Information Officers (CIOs). They are typically strategic business leaders responsible for driving growth and transformation through technology.)"
    },
    "hygiene_scorecard": {
      "tier": "Industry",
      "final_score": 7.4,
      "brand_health_index": 6.44,
      "trust_gap": 0.3,
      "audited_ts": "2025-06-21",
      "detailed_scores": {
        "|_corporate_positioning_alignment": {
          "score": 8,
          "rationale": "The page reflects Sopra Steria's focus on enabling digital transformation and leveraging technologies like AI and data analytics to drive business value. This aligns well with the persona's priorities around innovation and transformation. Example: \"Sopra Steria harnesses AI and autonomous transport to improve efficiency and customer experience as you build the future of transport.\""
        },
        "brand_differentiation": {
          "score": 6,
          "rationale": "While the page mentions some differentiating capabilities like AI expertise and rapid application development, it lacks quantified proof points or case studies that would make Sopra Steria stand out from competitors targeting the same industries. The messaging is still somewhat generic."
        },
        "value_proposition_clarity": {
          "score": 7,
          "rationale": "The page articulates a fairly clear value proposition around providing comprehensive digital solutions, supply chain expertise, and rapid application development to streamline processes and drive innovation. However, the benefits could be expressed in a more tangible, measurable way to resonate with the C-suite persona."
        },
        "trust_&_credibility_signals": {
          "score": 7,
          "rationale": "The client logos and success stories provide some credibility. However, more specific metrics, awards, analyst recognition or executive thought leadership content would help build trust with the senior executive audience."
        },
        "call-to-action_effectiveness": {
          "score": 8,
          "rationale": "The \"Let's Talk\" CTA is prominently featured and the contact form at the bottom of the page makes it easy to get in touch. Offering an executive-level content asset could further incentivize the target persona to engage."
        }
      },
      "recommendations": []
    },
    "experience_report": {
      "overall_sentiment": "Neutral",
      "engagement_level": "Low",
      "conversion_likelihood": "Low",
      "effective_copy": [
        {
          "text": "\"Sopra Steria harnesses AI and autonomous transport to improve efficiency and customer experience as you build the future of transport.\"",
          "analysis": "As a technology leader, this copy resonates by highlighting concrete capabilities (AI, autonomous transport) that align with my priorities to improve operational efficiency and customer experience through innovation. It positions Sopra Steria as a forward-thinking partner."
        },
        {
          "text": "\"With Sopra Steria, you'll benefit from unparalleled professional excellence, people-centric solutions and inspiring innovations that are redefining the future of industry, manufacturing, logistics, retail and telecom.\"",
          "analysis": "This copy is effective in conveying Sopra Steria's differentiated expertise and innovative mindset across industries relevant to me. The emphasis on \"people-centric solutions\" and \"redefining the future\" aligns well with my mission to leverage technology for business transformation."
        }
      ],
      "ineffective_copy": [
        {
          "text": "\"Let's talk\"",
          "analysis": "As a CTO/CDO, this generic call-to-action does not compel me to engage further. It lacks specificity on what value a conversation would provide to help me drive transformation and growth through technology."
        },
        {
          "text": "\"Our comprehensive digital solutions help to streamline processes, drive innovation and increase business value.\"",
          "analysis": "While this touches on some of my high-level objectives, it is too vague. As a CTO/CDO, I need to understand the specific solutions and proven outcomes to assess business value and alignment with my digital transformation roadmap."
        }
      ],
      "first_impression": "",
      "strategic_analysis": ""
    },
    "embeddings_content": {
      "combined_analysis": "HYGIENE SCORECARD:\n# Brand Hygiene Scorecard\n\n**URL:** https://www.soprasteria.be/industries/industry-retail-logistics-telecom-media\n**Persona:** Unknown Persona (This persona encompasses Chief Technology Officers (CTOs), Chief Digital Officers (CDOs), and their C-suite peers, such as Chief Information Officers (CIOs). They are typically strategic business leaders responsible for driving growth and transformation through technology.)\n**Audited:** 2025-06-21 15:57:55\n\n---\n\n## Overall Assessment\n\n- **Tier/Channel:** Industry Solutions Page\n- **Final Score:** 7.4/10\n\n---\n\n## Detailed Scoring\n\n| Category | Score | Rationale |\n| -------- | ----- | --------- |\n| Corporate Positioning Alignment | 8 | The page reflects Sopra Steria's focus on enabling digital transformation and leveraging technologies like AI and data analytics to drive business value. This aligns well with the persona's priorities around innovation and transformation. Example: \"Sopra Steria harnesses AI and autonomous transport to improve efficiency and customer experience as you build the future of transport.\" |\n| Brand Differentiation | 6 | While the page mentions some differentiating capabilities like AI expertise and rapid application development, it lacks quantified proof points or case studies that would make Sopra Steria stand out from competitors targeting the same industries. The messaging is still somewhat generic. |\n| Value Proposition Clarity | 7 | The page articulates a fairly clear value proposition around providing comprehensive digital solutions, supply chain expertise, and rapid application development to streamline processes and drive innovation. However, the benefits could be expressed in a more tangible, measurable way to resonate with the C-suite persona. |\n| Trust & Credibility Signals | 7 | The client logos and success stories provide some credibility. However, more specific metrics, awards, analyst recognition or executive thought leadership content would help build trust with the senior executive audience. |\n| Call-to-Action Effectiveness | 8 | The \"Let's Talk\" CTA is prominently featured and the contact form at the bottom of the page makes it easy to get in touch. Offering an executive-level content asset could further incentivize the target persona to engage. |\n\n---\n\n## Summary Rationale\n\nThe industry solutions page demonstrates good alignment with Sopra Steria's overall brand positioning around digital transformation and showcases relevant capabilities for the target industries. The value proposition around comprehensive solutions, supply chain expertise and application development comes across but could be articulated in a more persona-resonant way.\n\nWhile there are some proof points, the page lacks the degree of differentiation and credibility building that would make it truly stand out to a C-suite technology decision maker. Providing more tangible success metrics, recognised brand name clients, and thought leadership content would enhance the persuasive impact.\n\nThe page makes it easy to get in touch but adding an executive-focused content offer could help drive higher quality engagement with the senior persona.\n\n---\n\n## Priority Recommendations\n\n1. **Strengthen differentiation** - Highlight more unique or quantified proof points around Sopra Steria's capabilities in AI, supply chain, and application development to stand out from competitors.\n2. **Enhance credibility for C-suite** - Feature more recognised client names, specific success metrics, analyst recognition and executive thought leadership content to build trust with senior decision makers.  \n3. **Refine value proposition** - Evolve the value proposition messaging to focus on more tangible, measurable business outcomes that align with C-level priorities like revenue growth, cost reduction, and risk mitigation.\n\nEXPERIENCE REPORT:\n| Finding          | Example from Text | Strategic Analysis (from Persona's View)            |\n| ---------------- | ----------------- | --------------------------------------------------- |\n| Ineffective Copy | \"Let's talk\"      | As a CTO/CDO, this generic call-to-action does not compel me to engage further. It lacks specificity on what value a conversation would provide to help me drive transformation and growth through technology. |\n| Effective Copy   | \"Sopra Steria harnesses AI and autonomous transport to improve efficiency and customer experience as you build the future of transport.\"      | As a technology leader, this copy resonates by highlighting concrete capabilities (AI, autonomous transport) that align with my priorities to improve operational efficiency and customer experience through innovation. It positions Sopra Steria as a forward-thinking partner.    |\n| Ineffective Copy | \"Our comprehensive digital solutions help to streamline processes, drive innovation and increase business value.\" | While this touches on some of my high-level objectives, it is too vague. As a CTO/CDO, I need to understand the specific solutions and proven outcomes to assess business value and alignment with my digital transformation roadmap. |\n| Effective Copy | \"With Sopra Steria, you'll benefit from unparalleled professional excellence, people-centric solutions and inspiring innovations that are redefining the future of industry, manufacturing, logistics, retail and telecom.\" | This copy is effective in conveying Sopra Steria's differentiated expertise and innovative mindset across industries relevant to me. The emphasis on \"people-centric solutions\" and \"redefining the future\" aligns well with my mission to leverage technology for business transformation. |\n\nFirst-Person Analysis:\n\nUpon reviewing this webpage as a CTO/CDO, my initial impression is mixed. While there are some elements that resonate, such as the emphasis on AI, data-driven solutions, and industry-specific expertise, the overall value proposition for a technology leader like myself is not immediately clear. The language is professional but often lacks the specificity and proof points I would need to assess fit with my strategic priorities and transformation roadmap.\n\nThe copy effectively highlights some capabilities that align with my focus areas, such as harnessing AI and data analytics to drive efficiency and innovation. However, it falls short in detailing the concrete solutions, delivery model, and client outcomes that would allow me to build a compelling business case. As a CTO/CDO, I am looking for a partner that can provide both strategic vision and seamless execution to help me navigate complex challenges like legacy modernization, talent shortages, and rapidly evolving customer expectations. The page would benefit from more tangible examples and success stories to instill confidence.\n\nIn terms of building trust and credibility, the page makes positive strides by conveying deep industry knowledge and a forward-looking perspective. The client logos and mention of strategic partnerships lend some credibility. However, to fully earn my trust, I would need to see more substance behind the claims - such as proven methodologies, technology accelerators, and transformation case studies that showcase measurable business impact. Providing a clearer picture of the end-to-end engagement process and collaborative model would also help me envision the path forward. Ultimately, while this page piques some interest, it leaves me with more questions than answers. To compel a technology leader like myself to engage, I would recommend sharpening the value proposition, backing up claims with proof points, and painting a more vivid picture of the transformation journey and outcomes a CTO/CDO could achieve with Sopra Steria as their partner.",
      "key_themes": [
        "trust",
        "innovation",
        "risk"
      ],
      "business_impact": ""
    },
    "metadata": {
      "persona_id": "the_benelux_technology_innovation_leader",
      "page_id": "b53c7bea",
      "tier": "industry",
      "final_score": 7.4,
      "domain": "www.soprasteria.be",
      "content_type": "industry",
      "regulatory_frameworks": [],
      "is_benelux": true,
      "has_compliance_content": false,
      "has_security_content": false,
      "compiled_at": "2025-07-03T07:43:07.400660"
    }
  },
  {
    "page_id": "6be18313",
    "url": "https://www.soprasteria.nl/newsroom/blog",
    "slug": "wwwsoprasterianlnewsroomblog",
    "persona": {
      "name": "The_BENELUX_Technology_Innovation_Leader",
      "description": "Unknown Persona (This persona encompasses Chief Technology Officers (CTOs), Chief Digital Officers (CDOs), and their C-suite peers, such as Chief Information Officers (CIOs). They are typically strategic business leaders responsible for driving growth and transformation through technology.)"
    },
    "hygiene_scorecard": {
      "tier": "Thought",
      "final_score": 7.2,
      "brand_health_index": 6.32,
      "trust_gap": 0.2,
      "audited_ts": "2025-06-21",
      "detailed_scores": {
        "|_corporate_positioning_alignment": {
          "score": 8,
          "rationale": "The blog covers key topics like AI, digital transformation, and cybersecurity that align with Sopra Steria's positioning as a leader in digital transformation consulting. However, the connection to the company's specific approach and offerings could be stronger."
        },
        "brand_differentiation": {
          "score": 6,
          "rationale": "While the content is professional and covers relevant topics, it lacks a strong, differentiated point of view compared to other technology consulting firms. The Sopra Steria perspective and methodology is not clearly articulated."
        },
        "value_proposition_clarity": {
          "score": 7,
          "rationale": "The blog provides useful insights on important technology trends and business issues that would be relevant for CTOs and CDOs. However, the specific value proposition for how Sopra Steria can help is not always explicit in each post."
        },
        "trust_&_credibility_signals": {
          "score": 8,
          "rationale": "The authors are identified and appear to be knowledgeable subject matter experts. Client examples and case studies help build credibility. More hard data points and research citations would further strengthen trust."
        },
        "call-to-action_effectiveness": {
          "score": 7,
          "rationale": "While some posts mention Sopra Steria's offerings in passing, there are no clear next steps or calls-to-action for readers to engage further with the company. Adding relevant CTAs could improve lead generation."
        }
      },
      "recommendations": []
    },
    "experience_report": {
      "overall_sentiment": "Neutral",
      "engagement_level": "Low",
      "conversion_likelihood": "Low",
      "effective_copy": [
        {
          "text": "\"AI beyond the hype: what the Microsoft AI Tour Brussels taught us about moving beyond proof of concept to full-scale deployment\"",
          "analysis": "As a Technology & Innovation Leader, I appreciate content that cuts through the AI hype and provides practical insights on moving from POCs to production deployments. This headline suggests the article will share learnings and best practices that are directly relevant to my AI transformation goals."
        },
        {
          "text": "\"The power of semantics: how reliable data transforms AI\"",
          "analysis": "Connecting data reliability to AI outcomes aligns well with my priorities. I'm always looking for ways to harness data and AI to unlock tangible business value. This headline promises insights on how quality data can enhance AI initiatives, which is very relevant for me."
        }
      ],
      "ineffective_copy": [
        {
          "text": "\"Will your company survive the AI revolution?\"",
          "analysis": "As a strategic business leader responsible for driving growth and transformation through technology, this headline feels alarmist and vague. It doesn't provide any tangible information about how AI can deliver business value, which is my primary focus."
        },
        {
          "text": "\"Data poisoning: the phantom menace\"",
          "analysis": "While data quality is an important issue, this Star Wars reference feels out of place for a serious technology discussion. As a C-suite leader, I prefer more straightforward, business-oriented language."
        }
      ],
      "first_impression": "",
      "strategic_analysis": ""
    },
    "embeddings_content": {
      "combined_analysis": "HYGIENE SCORECARD:\n# Brand Hygiene Scorecard\n\n**URL:** https://www.soprasteria.nl/newsroom/blog\n**Persona:** Unknown Persona (This persona encompasses Chief Technology Officers (CTOs), Chief Digital Officers (CDOs), and their C-suite peers, such as Chief Information Officers (CIOs). They are typically strategic business leaders responsible for driving growth and transformation through technology.)\n**Audited:** 2025-06-21 16:00:45\n\n---\n\n## Overall Assessment\n\n- **Tier/Channel:** Thought Leadership Blog \n- **Final Score:** 7.2/10\n\n---\n\n## Detailed Scoring\n\n| Category | Score | Rationale |\n| -------- | ----- | --------- |\n| Corporate Positioning Alignment | 8 | The blog covers key topics like AI, digital transformation, and cybersecurity that align with Sopra Steria's positioning as a leader in digital transformation consulting. However, the connection to the company's specific approach and offerings could be stronger. |\n| Brand Differentiation | 6 | While the content is professional and covers relevant topics, it lacks a strong, differentiated point of view compared to other technology consulting firms. The Sopra Steria perspective and methodology is not clearly articulated. |\n| Value Proposition Clarity | 7 | The blog provides useful insights on important technology trends and business issues that would be relevant for CTOs and CDOs. However, the specific value proposition for how Sopra Steria can help is not always explicit in each post. |\n| Trust & Credibility Signals | 8 | The authors are identified and appear to be knowledgeable subject matter experts. Client examples and case studies help build credibility. More hard data points and research citations would further strengthen trust. |\n| Call-to-Action Effectiveness | 7 | While some posts mention Sopra Steria's offerings in passing, there are no clear next steps or calls-to-action for readers to engage further with the company. Adding relevant CTAs could improve lead generation. |\n\n---\n\n## Summary Rationale\n\nThe Sopra Steria blog covers topics that would be of interest to technology executives looking to drive digital transformation, such as AI, cybersecurity, cloud, and data analytics. The content is professional and shows good subject matter expertise.\n\nHowever, to truly stand out for this senior executive persona, the blog could do more to showcase Sopra Steria's unique perspective and methodology. The value proposition for how the company helps clients achieve results is not always clear. \n\nBuilding in more client proof points, research data, and clear next steps would elevate the blog from good to great for this audience. With a few tweaks to better highlight differentiation and provide clearer calls-to-action, this could become a powerful thought leadership channel.\n\n---\n\n## Priority Recommendations\n\n1. **Differentiated viewpoint** - Articulate Sopra Steria's unique perspective and approach more clearly in each post to stand out from other technology consultancies.\n\n2. **Strengthen value proposition** - Tie the insights in each post back to the specific value Sopra Steria delivers and how you help clients succeed. Make the \"so what\" clear.\n\n3. **Add calls-to-action** - Provide relevant next steps in each post to engage readers further, such as links to related content, invitations to events, or offers to discuss their specific challenges with an expert.\n\nEXPERIENCE REPORT:\n| Finding          | Example from Text | Strategic Analysis (from Persona's View)            |\n| ---------------- | ----------------- | --------------------------------------------------- |\n| Ineffective Copy | \"Will your company survive the AI revolution?\" | As a strategic business leader responsible for driving growth and transformation through technology, this headline feels alarmist and vague. It doesn't provide any tangible information about how AI can deliver business value, which is my primary focus. |\n| Effective Copy   | \"AI beyond the hype: what the Microsoft AI Tour Brussels taught us about moving beyond proof of concept to full-scale deployment\"  | As a Technology & Innovation Leader, I appreciate content that cuts through the AI hype and provides practical insights on moving from POCs to production deployments. This headline suggests the article will share learnings and best practices that are directly relevant to my AI transformation goals.    |\n| Ineffective Copy | \"Data poisoning: the phantom menace\" | While data quality is an important issue, this Star Wars reference feels out of place for a serious technology discussion. As a C-suite leader, I prefer more straightforward, business-oriented language. |\n| Effective Copy   | \"The power of semantics: how reliable data transforms AI\" | Connecting data reliability to AI outcomes aligns well with my priorities. I'm always looking for ways to harness data and AI to unlock tangible business value. This headline promises insights on how quality data can enhance AI initiatives, which is very relevant for me. |\n\nFirst-Person Narrative Analysis:\n\nAs a Technology & Innovation Leader scanning this blog, my first impression is that the content is hit-or-miss in terms of addressing my strategic priorities and pain points. Some articles, like the one on moving AI from POCs to production, appear to offer valuable insights that could help me drive transformation at scale. However, other headlines come across as either sensationalized click-bait or overly technical discussions that fail to tie back to business outcomes.\n\nThe language and tone are inconsistent. While I appreciate the attempt to be engaging with pop culture references and provocative questions, at times it veers too far into hype and buzz for my taste. I'm looking for content that is direct, substantive, and focused on real-world applications and results. The most effective examples are those that connect technology topics like data platforms and AI directly to use cases and value creation.\n\nOne key thing I find missing is more case studies and proof points featuring companies that have successfully navigated the challenges I'm facing, such as legacy system modernization and talent shortages. I'd like to see more specifics on how they are measuring the ROI of their technology investments and managing risk. Customer stories from my industry and region would be especially powerful in building trust and confidence to move forward with similar initiatives.\n\nOverall, this blog leaves me with mixed feelings. While there are some bright spots, the lack of consistency and depth makes me question how well this company understands my world and whether they have the expertise to be a trusted partner. To improve, I'd recommend they refine their content strategy to focus on the topics and approaches that will resonate most with enterprise decision-makers. They should strip away the gimmicks and let the customer successes speak for themselves. By demonstrating a strong grasp of my business realities and a track record of delivering results, they'll be in a much better position to earn my trust and business.",
      "key_themes": [
        "trust",
        "security",
        "innovation",
        "risk"
      ],
      "business_impact": ""
    },
    "metadata": {
      "persona_id": "the_benelux_technology_innovation_leader",
      "page_id": "6be18313",
      "tier": "thought",
      "final_score": 7.2,
      "domain": "www.soprasteria.nl",
      "content_type": "blog",
      "regulatory_frameworks": [],
      "is_benelux": true,
      "has_compliance_content": false,
      "has_security_content": true,
      "compiled_at": "2025-07-03T07:43:07.401383"
    }
  },
  {
    "page_id": "4fb3c324",
    "url": "https://www.soprasteria.nl/newsroom/press-releases/details/welcome-to-the-future-of-innovation",
    "slug": "wwwsoprasterianlnewsroompress-releasesdetailswelcome-to-the-future-of-innovation",
    "persona": {
      "name": "The_BENELUX_Technology_Innovation_Leader",
      "description": "Unknown Persona (This persona encompasses Chief Technology Officers (CTOs), Chief Digital Officers (CDOs), and their C-suite peers, such as Chief Information Officers (CIOs). They are typically strategic business leaders responsible for driving growth and transformation through technology.)"
    },
    "hygiene_scorecard": {
      "tier": "Press",
      "final_score": 5.2,
      "brand_health_index": 5.12,
      "trust_gap": 0.6,
      "audited_ts": "2025-06-21",
      "detailed_scores": {
        "|_corporate_positioning_alignment": {
          "score": 6,
          "rationale": "The page mentions some key themes relevant to the persona like AI, cybersecurity, and digital transformation. However, it lacks a clear articulation of Sopra Steria's unique positioning and approach in these areas. More specificity is needed on how they enable \"Confident Momentum\" for clients."
        },
        "brand_differentiation": {
          "score": 4,
          "rationale": "Very little content to differentiate Sopra Steria from other major tech services firms. Broad claims about being \"a major Tech player in Europe\" but no substantiation of what makes their offerings superior. CTOs need to see more distinctive capabilities."
        },
        "value_proposition_clarity": {
          "score": 5,
          "rationale": "The title \"Welcome to the Future of Innovation\" suggests a forward-looking perspective aligned with the persona. But the body content is extremely sparse - no details on what specific types of innovation Sopra Steria enables for clients and the business outcomes delivered. Needs much more meat."
        },
        "trust_&_credibility_signals": {
          "score": 4,
          "rationale": "Lack of any tangible proof points, case studies, analyst validations, etc. that would give a CTO confidence. Simply saying they are \"recognised for its consulting, digital services and solutions\" is not enough - recognized by whom? No hard evidence to support trustworthiness."
        },
        "call-to-action_effectiveness": {
          "score": 7,
          "rationale": "The \"Related content\" links to topics like AI, cybersecurity and digital banking are useful for the persona to learn more. But no clear next step on how to directly engage with Sopra Steria for these kinds of innovation initiatives. A \"Contact Us\" or \"Request a Consultation\" CTA would improve this score."
        }
      },
      "recommendations": []
    },
    "experience_report": {
      "overall_sentiment": "Neutral",
      "engagement_level": "Low",
      "conversion_likelihood": "Low",
      "effective_copy": [
        {
          "text": "\"Discover how AI is revolutionizing cybersecurity and giving you a strategic edge.\"",
          "analysis": "As a technology leader balancing innovation with security, this directly addresses one of my key priorities. It positions AI as a strategic enabler rather than just a buzzword. I would be interested to learn more about their specific AI-driven cybersecurity solutions."
        },
        {
          "text": "\"Transforming public services for a citizen-centric future: robust, agile, effective, and connected.\"",
          "analysis": "Although my role is not in the public sector, this copy demonstrates an understanding of the key attributes (robust, agile, effective, connected) that matter to technology leaders like myself. It shows they can frame their solutions in terms of tangible business and customer outcomes."
        }
      ],
      "ineffective_copy": [
        {
          "text": "\"Welcome to the Future of Innovation\"",
          "analysis": "As a technology & innovation leader, this headline feels generic and lacks a clear value proposition for my role and priorities. It doesn't speak to how the company will tangibly enable innovation."
        },
        {
          "text": "\"Sopra Steria, a major Tech player in Europe with 50,000 employees in nearly 30 countries, is recognised for its consulting, digital services and solutions.\"",
          "analysis": "While the company's scale and capabilities may be impressive, as a C-suite leader I need to understand how those translate into specific business outcomes and competitive advantages for my organization. Size alone is not a compelling differentiator."
        }
      ],
      "first_impression": "",
      "strategic_analysis": ""
    },
    "embeddings_content": {
      "combined_analysis": "HYGIENE SCORECARD:\n# Brand Hygiene Scorecard\n\n**URL:** https://www.soprasteria.nl/newsroom/press-releases/details/welcome-to-the-future-of-innovation\n**Persona:** Unknown Persona (This persona encompasses Chief Technology Officers (CTOs), Chief Digital Officers (CDOs), and their C-suite peers, such as Chief Information Officers (CIOs). They are typically strategic business leaders responsible for driving growth and transformation through technology.)\n**Audited:** 2025-06-21 15:58:49\n\n---\n\n## Overall Assessment\n\n- **Tier/Channel:** Press Release\n- **Final Score:** 5.2/10\n\n---\n\n## Detailed Scoring\n\n| Category | Score | Rationale |\n| -------- | ----- | --------- |\n| Corporate Positioning Alignment | 6 | The page mentions some key themes relevant to the persona like AI, cybersecurity, and digital transformation. However, it lacks a clear articulation of Sopra Steria's unique positioning and approach in these areas. More specificity is needed on how they enable \"Confident Momentum\" for clients. |\n| Brand Differentiation | 4 | Very little content to differentiate Sopra Steria from other major tech services firms. Broad claims about being \"a major Tech player in Europe\" but no substantiation of what makes their offerings superior. CTOs need to see more distinctive capabilities. |\n| Value Proposition Clarity | 5 | The title \"Welcome to the Future of Innovation\" suggests a forward-looking perspective aligned with the persona. But the body content is extremely sparse - no details on what specific types of innovation Sopra Steria enables for clients and the business outcomes delivered. Needs much more meat. |\n| Trust & Credibility Signals | 4 | Lack of any tangible proof points, case studies, analyst validations, etc. that would give a CTO confidence. Simply saying they are \"recognised for its consulting, digital services and solutions\" is not enough - recognized by whom? No hard evidence to support trustworthiness. |\n| Call-to-Action Effectiveness | 7 | The \"Related content\" links to topics like AI, cybersecurity and digital banking are useful for the persona to learn more. But no clear next step on how to directly engage with Sopra Steria for these kinds of innovation initiatives. A \"Contact Us\" or \"Request a Consultation\" CTA would improve this score. |\n\n---\n\n## Summary Rationale\n\nFor a C-level technology leader seeking to drive major transformation, this press release page is quite underwhelming. While it touches on some high-level themes of interest to the persona like AI and digital innovation, it is severely lacking in specifics on Sopra Steria's differentiated capabilities in these areas and the concrete value they deliver to enterprise clients. \n\nThere are no proof points to establish credibility, nor a clear articulation of what makes Sopra Steria's approach uniquely effective compared to other major players. Much more detail is needed on their distinctive offerings, methodologies, client success stories, and expert perspectives to give a CTO confidence that Sopra Steria should be a trusted partner for strategic innovation initiatives.\n\nThe page also misses an opportunity to engage the persona in a meaningful next step. Links to related content are provided, but no direct call-to-action to have a conversation with Sopra Steria on the CTO's specific innovation agenda and challenges. Overall, significant improvements in messaging specificity, differentiation and credibility are recommended to turn this into an effective CTO-facing asset.\n\n---\n\n## Priority Recommendations\n\n1. **Weak Differentiation** - Expand messaging to clearly articulate Sopra Steria's unique capabilities and approach to AI, cybersecurity, digital transformation etc. What concrete differentiators enable them to drive innovation success for clients better than alternatives?\n\n2. **Lack of Proof** - Add credibility-building content like client case studies, analyst quotes, and key facts/figures that validate Sopra Steria's expertise in delivering CTO-relevant innovation. Prove the claims with real evidence.\n\n3. **Unclear Next Steps** - Include a prominent call-to-action for CTOs to directly connect with Sopra Steria experts on their innovation goals and challenges. Make it easy to request a consultation or conversation to learn more.\n\nEXPERIENCE REPORT:\n| Finding          | Example from Text | Strategic Analysis (from Persona's View)            |\n| ---------------- | ----------------- | --------------------------------------------------- |\n| Ineffective Copy | \"Welcome to the Future of Innovation\"      | As a technology & innovation leader, this headline feels generic and lacks a clear value proposition for my role and priorities. It doesn't speak to how the company will tangibly enable innovation.  |\n| Ineffective Copy   | \"Sopra Steria, a major Tech player in Europe with 50,000 employees in nearly 30 countries, is recognised for its consulting, digital services and solutions.\"      | While the company's scale and capabilities may be impressive, as a C-suite leader I need to understand how those translate into specific business outcomes and competitive advantages for my organization. Size alone is not a compelling differentiator.    |\n| Effective Copy | \"Discover how AI is revolutionizing cybersecurity and giving you a strategic edge.\"      | As a technology leader balancing innovation with security, this directly addresses one of my key priorities. It positions AI as a strategic enabler rather than just a buzzword. I would be interested to learn more about their specific AI-driven cybersecurity solutions. |\n| Effective Copy   | \"Transforming public services for a citizen-centric future: robust, agile, effective, and connected.\"     | Although my role is not in the public sector, this copy demonstrates an understanding of the key attributes (robust, agile, effective, connected) that matter to technology leaders like myself. It shows they can frame their solutions in terms of tangible business and customer outcomes.  |\n\nFirst-Person Narrative Analysis:\n\nAs a Chief Technology Officer, my initial impression of this webpage is mixed. While it touches on some of the right themes around innovation, AI, and cybersecurity, the overall messaging feels somewhat generic and high-level for a C-suite audience. The headline \"Welcome to the Future of Innovation\" is catchy but lacks substance. As a technology leader, I need to quickly understand how this company's specific capabilities will drive innovation and deliver measurable business results.\n\nThe page does a better job when it gets into more concrete examples, such as how AI can provide a strategic edge in cybersecurity. This aligns with my priority of balancing transformative innovation with robust security and compliance. However, I would need more details and proof points on their AI-driven solutions to build real confidence. Similarly, while the mention of transforming public services demonstrates an outcome-oriented approach, it's not directly relevant to my industry.\n\nIn terms of gaps, I don't see a clear articulation of what truly differentiates this company from other large technology players. The focus on their size and broad capabilities, while notable, doesn't tell me what unique value they would bring to my organization's specific challenges, such as legacy modernization or harnessing data for business insights. To move forward, I would need to see more tailored messaging around their proven ability to deliver results for C-level leaders in my industry and region.\n\nOverall, this page leaves me with a neutral impression. It shows some promise in terms of themes and examples but lacks the depth, specificity, and sharp focus on business outcomes that I require as a CTO. To improve, I would recommend:\n\n1) Replacing generic headlines with concrete value propositions aligned to C-suite priorities \n2) Providing more detailed case studies and proof points of enabling innovation and transformation for similar companies\n3) Tailoring the content and language to resonate with industry- and role-specific challenges\n4) Clearly articulating their differentiated capabilities and approach compared to other major players\n\nWith these enhancements, the page could more effectively engage and persuade technology leaders like myself that this is a company uniquely equipped to drive our innovation and transformation agendas forward.",
      "key_themes": [
        "trust",
        "security",
        "compliance",
        "innovation"
      ],
      "business_impact": ""
    },
    "metadata": {
      "persona_id": "the_benelux_technology_innovation_leader",
      "page_id": "4fb3c324",
      "tier": "press",
      "final_score": 5.2,
      "domain": "www.soprasteria.nl",
      "content_type": "news",
      "regulatory_frameworks": [],
      "is_benelux": true,
      "has_compliance_content": true,
      "has_security_content": true,
      "compiled_at": "2025-07-03T07:43:07.402747"
    }
  },
  {
    "page_id": "f52cdbdc",
    "url": "https://www.soprasteria.nl/newsroom/blog/details/interacting-with-large-language-models",
    "slug": "wwwsoprasterianlnewsroomblogdetailsinteracting-with-large-language-models",
    "persona": {
      "name": "The_BENELUX_Technology_Innovation_Leader",
      "description": "Unknown Persona (This persona encompasses Chief Technology Officers (CTOs), Chief Digital Officers (CDOs), and their C-suite peers, such as Chief Information Officers (CIOs). They are typically strategic business leaders responsible for driving growth and transformation through technology.)"
    },
    "hygiene_scorecard": {
      "tier": "Thought",
      "final_score": 7.8,
      "brand_health_index": 6.68,
      "trust_gap": 0.3,
      "audited_ts": "2025-06-21",
      "detailed_scores": {
        "|_corporate_positioning_alignment": {
          "score": 8,
          "rationale": "The blog post aligns well with Sopra Steria's positioning as a technology leader driving business transformation. It showcases their expertise in AI and provides practical advice for leveraging LLMs. However, it could tie the content back to Sopra Steria's specific offerings and capabilities more explicitly."
        },
        "brand_differentiation": {
          "score": 7,
          "rationale": "The post demonstrates Sopra Steria's deep knowledge of LLMs and provides actionable strategies. This helps differentiate them as an authority. However, the advice is still somewhat generic and could apply to any AI consultancy. Highlighting Sopra Steria's unique methodologies or client successes would boost differentiation."
        },
        "value_proposition_clarity": {
          "score": 8,
          "rationale": "For CTOs and digital leaders looking to harness LLMs, the post delivers a clear value prop: 5 concrete ways to get better results from AI investments. The tips are relevant and impactful for the persona's goals. More quantification of potential benefits would strengthen the value prop further."
        },
        "trust_&_credibility_signals": {
          "score": 7,
          "rationale": "The authoritative tone, clear explanations, and practical examples convey expertise that builds trust. However, there are no hard proof points like data, case studies, or author credentials to cement credibility. Adding these elements would enhance trust, especially for a senior executive audience."
        },
        "call-to-action_effectiveness": {
          "score": 7,
          "rationale": "The post ends abruptly without a clear next step for the reader. While the \"Related content\" links are topically relevant, there is no direct CTA to contact Sopra Steria or access further LLM resources. Adding a prominent \"Get started\" CTA linking to a consultation offer or gated content would improve engagement."
        }
      },
      "recommendations": []
    },
    "experience_report": {
      "overall_sentiment": "Neutral",
      "engagement_level": "Low",
      "conversion_likelihood": "Low",
      "effective_copy": [
        {
          "text": "\"Sopra Steria, a major Tech player in Europe with 50,000 employees in nearly 30 countries, is recognised for its consulting, digital services and solutions.\"",
          "analysis": "As a CTO/CDO, Sopra Steria's scale, geographic reach, and breadth of offerings are compelling. This positions them as a potential strategic partner to help me navigate complex digital initiatives. However, I still need more details on their specific AI and data capabilities to fully assess fit."
        }
      ],
      "ineffective_copy": [
        {
          "text": "\"The world is how we shape it\"",
          "analysis": "As a strategic technology leader, this tagline feels vague and lacks a clear connection to how Sopra Steria can tangibly help me drive digital transformation and business value. I need more specifics on their unique capabilities and track record."
        }
      ],
      "first_impression": "",
      "strategic_analysis": ""
    },
    "embeddings_content": {
      "combined_analysis": "HYGIENE SCORECARD:\n# Brand Hygiene Scorecard\n\n**URL:** https://www.soprasteria.nl/newsroom/blog/details/interacting-with-large-language-models\n**Persona:** Unknown Persona (This persona encompasses Chief Technology Officers (CTOs), Chief Digital Officers (CDOs), and their C-suite peers, such as Chief Information Officers (CIOs). They are typically strategic business leaders responsible for driving growth and transformation through technology.)\n**Audited:** 2025-06-21 16:01:38\n\n---\n\n## Overall Assessment\n\n- **Tier/Channel:** Thought Leadership Blog\n- **Final Score:** 7.8/10\n\n---\n\n## Detailed Scoring\n\n| Category | Score | Rationale |\n| -------- | ----- | --------- |\n| Corporate Positioning Alignment | 8 | The blog post aligns well with Sopra Steria's positioning as a technology leader driving business transformation. It showcases their expertise in AI and provides practical advice for leveraging LLMs. However, it could tie the content back to Sopra Steria's specific offerings and capabilities more explicitly. |\n| Brand Differentiation | 7 | The post demonstrates Sopra Steria's deep knowledge of LLMs and provides actionable strategies. This helps differentiate them as an authority. However, the advice is still somewhat generic and could apply to any AI consultancy. Highlighting Sopra Steria's unique methodologies or client successes would boost differentiation. |\n| Value Proposition Clarity | 8 | For CTOs and digital leaders looking to harness LLMs, the post delivers a clear value prop: 5 concrete ways to get better results from AI investments. The tips are relevant and impactful for the persona's goals. More quantification of potential benefits would strengthen the value prop further. |\n| Trust & Credibility Signals | 7 | The authoritative tone, clear explanations, and practical examples convey expertise that builds trust. However, there are no hard proof points like data, case studies, or author credentials to cement credibility. Adding these elements would enhance trust, especially for a senior executive audience. |\n| Call-to-Action Effectiveness | 7 | The post ends abruptly without a clear next step for the reader. While the \"Related content\" links are topically relevant, there is no direct CTA to contact Sopra Steria or access further LLM resources. Adding a prominent \"Get started\" CTA linking to a consultation offer or gated content would improve engagement. |\n\n---\n\n## Summary Rationale\n\nFor a CTO or digital leader exploring LLM opportunities, this blog post delivers valuable insights and practical advice from Sopra Steria's AI experts. The content aligns with the persona's priorities of driving innovation while ensuring robust implementation. \n\nKey strengths include:\n- Actionable strategies for getting better LLM results \n- Clear explanations of technical concepts like few-shot prompting and RAG\n- Relevant examples that illustrate the business benefits\n\nHowever, to fully resonate with a C-suite executive, the post should:\n- Tie the advice back to Sopra Steria's unique offerings and proven successes\n- Provide more hard proof points to validate expertise and impact\n- Include a clear next step for engaging Sopra Steria to start applying these practices\n\nWith a score of 7.8, this is a strong piece of thought leadership that positions Sopra Steria as an AI authority, but a few enhancements could optimize its impact and engagement with senior decision-makers.\n\n---\n\n## Priority Recommendations\n\n1. **Strengthen differentiation** - Highlight Sopra Steria's unique LLM methodologies, tools, or client results to stand out from generic AI advice.\n2. **Quantify the benefits** - Add data points on the business impact of applying these LLM strategies to make a more compelling case.\n3. **Add a clear CTA** - Include a prominent next step, such as a \"Get started\" button linking to a consultation offer or a gated LLM guide, to engage CTO readers.\n\nEXPERIENCE REPORT:\n| Finding          | Example from Text | Strategic Analysis (from Persona's View)            |\n| ---------------- | ----------------- | --------------------------------------------------- |\n| Ineffective Copy | \"The world is how we shape it\" | As a strategic technology leader, this tagline feels vague and lacks a clear connection to how Sopra Steria can tangibly help me drive digital transformation and business value. I need more specifics on their unique capabilities and track record. |\n| Effective Copy   | \"Sopra Steria, a major Tech player in Europe with 50,000 employees in nearly 30 countries, is recognised for its consulting, digital services and solutions.\" | As a CTO/CDO, Sopra Steria's scale, geographic reach, and breadth of offerings are compelling. This positions them as a potential strategic partner to help me navigate complex digital initiatives. However, I still need more details on their specific AI and data capabilities to fully assess fit. |\n\nAs a Chief Technology Officer tasked with driving digital transformation, my first impression of this Sopra Steria blog post is mixed. The topic of effectively leveraging Large Language Models is highly relevant to my AI innovation priorities. However, the lack of a clear, upfront value proposition leaves me unsure if investing more time here will deliver the strategic insights I need.\n\nThe post does provide useful technical tips, like few-shot prompting and function calling, which could help my team optimize our LLM interactions. This demonstrates some credible expertise. However, the language often drifts into generic statements rather than the incisive, outcome-focused guidance I'm seeking as a technology leader. Critically, there is a missed opportunity to tie these LLM best practices back to delivering measurable business value - my core mandate.\n\nTo build my confidence and engagement, I would recommend Sopra Steria enhance this piece with more industry-specific proof points and concrete examples of how optimized LLM usage has driven strategic wins for organizations like mine. Highlighting a few brief but impactful case studies would help me envision the tangible potential for my own digital transformation efforts. Additionally, acknowledging common challenges technology leaders face when implementing AI, like talent gaps and legacy system integration, would further boost credibility by demonstrating an understanding of my reality. With some targeted improvements to better speak to my C-suite perspective, this piece could evolve from a general primer to an valuable strategic resource earning Sopra Steria a spot on my short list of potential AI partners.",
      "key_themes": [
        "trust",
        "innovation"
      ],
      "business_impact": ""
    },
    "metadata": {
      "persona_id": "the_benelux_technology_innovation_leader",
      "page_id": "f52cdbdc",
      "tier": "thought",
      "final_score": 7.8,
      "domain": "www.soprasteria.nl",
      "content_type": "blog",
      "regulatory_frameworks": [],
      "is_benelux": true,
      "has_compliance_content": false,
      "has_security_content": false,
      "compiled_at": "2025-07-03T07:43:07.403511"
    }
  },
  {
    "page_id": "ad80a76c",
    "url": "https://www.soprasteria.nl/",
    "slug": "wwwsoprasterianl",
    "persona": {
      "name": "The_BENELUX_Technology_Innovation_Leader",
      "description": "Unknown Persona (This persona encompasses Chief Technology Officers (CTOs), Chief Digital Officers (CDOs), and their C-suite peers, such as Chief Information Officers (CIOs). They are typically strategic business leaders responsible for driving growth and transformation through technology.)"
    },
    "hygiene_scorecard": {
      "tier": "Corporate",
      "final_score": 7.2,
      "brand_health_index": 6.32,
      "trust_gap": 0.2,
      "audited_ts": "2025-06-21",
      "detailed_scores": {
        "|_corporate_positioning_alignment": {
          "score": 8,
          "rationale": "The page reflects Sopra Steria's core brand message of shaping the world through technology fairly well, with statements like \"The world is how we shape it\" and emphasis on driving innovation. However, the connection between this high-level message and specific solutions could be stronger."
        },
        "brand_differentiation": {
          "score": 6,
          "rationale": "While the page mentions Sopra Steria's scale (51,000 employees in 30 countries) and some key solution areas, it lacks strong differentiation from other major technology consulting firms. More emphasis on unique strengths and successes with name-brand clients could help them stand out."
        },
        "value_proposition_clarity": {
          "score": 7,
          "rationale": "The value proposition around empowering clients to excel through process streamlining, productivity enhancement and innovation is somewhat clear but high-level and generic. Connecting this more explicitly to the target persona's key priorities around transformation, data/AI and security would strengthen resonance."
        },
        "trust_&_credibility_signals": {
          "score": 8,
          "rationale": "The page conveys credibility through highlighting scale, breadth of industries and solutions, and thought leadership content. Including more specific case studies, analyst ratings or awards could further boost trust. Surfacing key stats more prominently would also help."
        },
        "call-to-action_effectiveness": {
          "score": 7,
          "rationale": "While the persistent top navigation provides clear paths to learn more about industries, solutions and thought leadership content, the page lacks a strong CTA specifically tailored to the C-suite technology leader persona. Adding a prominent \"Contact Us\" or \"Request a Consultation\" CTA could improve conversion."
        }
      },
      "recommendations": []
    },
    "experience_report": {
      "overall_sentiment": "Neutral",
      "engagement_level": "Low",
      "conversion_likelihood": "Low",
      "effective_copy": [
        {
          "text": "\"The Future of Generative AI: Insights and Strategies for 2025. Our latest report offers a detailed analysis of the GenAI landscape, combining insights from various sources and Sopra Steria's AI specialists. It highlights key trends, technological advancements, and strategic recommendations for 2025.\"",
          "analysis": "As a CTO/CDO, I'm keenly interested in emerging technologies like generative AI and how they can be strategically leveraged to transform the business. This copy effectively grabs my attention by focusing on a highly relevant topic and providing a forward-looking perspective with actionable insights and recommendations tailored to my priorities."
        }
      ],
      "ineffective_copy": [
        {
          "text": "\"We empower you to excel by streamlining processes, enhancing productivity, and driving innovation in a dynamic business environment.\"",
          "analysis": "As a strategic C-suite technology leader, this high-level statement lacks specificity on how exactly Sopra Steria will help me achieve my key priorities of digital transformation and harnessing data/AI for business value. The language is vague and doesn't clearly articulate outcomes relevant to my role and challenges."
        }
      ],
      "first_impression": "",
      "strategic_analysis": ""
    },
    "embeddings_content": {
      "combined_analysis": "HYGIENE SCORECARD:\n# Brand Hygiene Scorecard\n\n**URL:** https://www.soprasteria.nl/\n**Persona:** Unknown Persona (This persona encompasses Chief Technology Officers (CTOs), Chief Digital Officers (CDOs), and their C-suite peers, such as Chief Information Officers (CIOs). They are typically strategic business leaders responsible for driving growth and transformation through technology.)\n**Audited:** 2025-06-21 15:48:21\n\n---\n\n## Overall Assessment\n\n- **Tier/Channel:** Corporate Website - Top-level \n- **Final Score:** 7.2/10\n\n---\n\n## Detailed Scoring\n\n| Category | Score | Rationale |\n| -------- | ----- | --------- |\n| Corporate Positioning Alignment | 8 | The page reflects Sopra Steria's core brand message of shaping the world through technology fairly well, with statements like \"The world is how we shape it\" and emphasis on driving innovation. However, the connection between this high-level message and specific solutions could be stronger. |\n| Brand Differentiation | 6 | While the page mentions Sopra Steria's scale (51,000 employees in 30 countries) and some key solution areas, it lacks strong differentiation from other major technology consulting firms. More emphasis on unique strengths and successes with name-brand clients could help them stand out. |\n| Value Proposition Clarity | 7 | The value proposition around empowering clients to excel through process streamlining, productivity enhancement and innovation is somewhat clear but high-level and generic. Connecting this more explicitly to the target persona's key priorities around transformation, data/AI and security would strengthen resonance. |\n| Trust & Credibility Signals | 8 | The page conveys credibility through highlighting scale, breadth of industries and solutions, and thought leadership content. Including more specific case studies, analyst ratings or awards could further boost trust. Surfacing key stats more prominently would also help. |\n| Call-to-Action Effectiveness | 7 | While the persistent top navigation provides clear paths to learn more about industries, solutions and thought leadership content, the page lacks a strong CTA specifically tailored to the C-suite technology leader persona. Adding a prominent \"Contact Us\" or \"Request a Consultation\" CTA could improve conversion. |\n\n---\n\n## Summary Rationale\n\nFor a C-suite technology leader seeking a partner to drive transformation through AI, data and security, Sopra Steria's website makes a competent but not fully compelling case. The company's scale and solution breadth come across, but the specific value proposition and differentiation for this persona's needs could be sharper. \n\nStrengths include the high-level alignment with the persona's innovation and transformation goals, and ample paths to learn more. Key gaps are the lack of a strong, persona-specific CTA and supporting proof points like case studies and stats to concretely illustrate capabilities.\n\nWith a bit more tailoring of the messaging and surfacing of credibility boosters, the page could become a powerful tool for engaging this critical persona. But in its current state, it may not fully motivate a CTO/CIO/CDO to choose Sopra Steria over competitors.\n\n---\n\n## Priority Recommendations\n\n1. **Sharpen the C-suite technology leader value proposition** - Explicitly connect Sopra Steria's capabilities to this persona's key priorities around transformation, AI/data, and security. Clarify how Sopra Steria is uniquely equipped to help technology leaders deliver results.\n\n2. **Showcase more proof points of success** - Feature 2-3 short case studies or testimonial quotes demonstrating impact for similar clients. Highlight any analyst recognition, awards or rankings to boost credibility. Call out a few key stats on clients transformed or value delivered.\n\n3. **Add a prominent persona-specific CTA** - Include a clear next step tailored to a C-suite technology leader, such as \"Request a CTO/CIO Consultation\" or \"Contact Us to Discuss Your Transformation Goals\". Make it easy for them to engage directly on their terms.\n\nEXPERIENCE REPORT:\nHere is my first-person strategic analysis of the webpage content from the perspective of the provided C-suite technology leader persona:\n\n| Finding          | Example from Text | Strategic Analysis (from Persona's View)            |\n| ---------------- | ----------------- | --------------------------------------------------- |\n| Ineffective Copy | \"We empower you to excel by streamlining processes, enhancing productivity, and driving innovation in a dynamic business environment.\" | As a strategic C-suite technology leader, this high-level statement lacks specificity on how exactly Sopra Steria will help me achieve my key priorities of digital transformation and harnessing data/AI for business value. The language is vague and doesn't clearly articulate outcomes relevant to my role and challenges. |\n| Effective Copy   | \"The Future of Generative AI: Insights and Strategies for 2025. Our latest report offers a detailed analysis of the GenAI landscape, combining insights from various sources and Sopra Steria's AI specialists. It highlights key trends, technological advancements, and strategic recommendations for 2025.\"   | As a CTO/CDO, I'm keenly interested in emerging technologies like generative AI and how they can be strategically leveraged to transform the business. This copy effectively grabs my attention by focusing on a highly relevant topic and providing a forward-looking perspective with actionable insights and recommendations tailored to my priorities. |\n\n**First-Person Narrative Analysis:**\n\nUpon reviewing the Sopra Steria Benelux webpage, my initial impression as a C-suite technology leader is mixed. While the page touches on some high-level themes relevant to my role, such as digital transformation, data & AI, and cybersecurity, the overall value proposition for how Sopra Steria can help me drive tangible business outcomes remains unclear. The language is often generic and fails to articulate specific benefits and proof points that would resonate with a strategic decision-maker like myself.\n\nThat said, there are some bright spots where the content does align with my key priorities. The featured report on generative AI strategies demonstrates thought leadership on an emerging technology with significant potential to reshape industries. As a CTO/CDO, I appreciate this forward-thinking perspective and emphasis on turning AI innovation into real-world impact. However, to fully capture my interest, I would need to see more substantive case studies and client stories that quantify the business results achieved, especially in areas like legacy modernization, data-driven transformation, and navigating talent/budget constraints.\n\nIn terms of building trust and credibility, the page leaves me wanting more. While the employee and office statistics aim to convey scale and stability, they don't address the more pressing concerns of a C-suite buyer - namely, how Sopra Steria's capabilities translate into a track record of successful delivery and value creation for clients. Highlighting strategic partnerships with key technology players and co-innovation initiatives would help strengthen confidence. Ultimately, to compel action from a technology leader like myself, the page needs to lead with a sharper, more differentiated message on why Sopra Steria is the ideal partner to enable and accelerate digital transformation in the face of my specific industry challenges. Grounding the content in a deeper understanding of my world - the pressures, the possibilities, the \"so what\" - will be critical to turning my interest into engagement.",
      "key_themes": [
        "trust",
        "security",
        "innovation"
      ],
      "business_impact": ""
    },
    "metadata": {
      "persona_id": "the_benelux_technology_innovation_leader",
      "page_id": "ad80a76c",
      "tier": "corporate",
      "final_score": 7.2,
      "domain": "www.soprasteria.nl",
      "content_type": "unknown",
      "regulatory_frameworks": [],
      "is_benelux": true,
      "has_compliance_content": false,
      "has_security_content": true,
      "compiled_at": "2025-07-03T07:43:07.404464"
    }
  },
  {
    "page_id": "d83b69a8",
    "url": "https://www.soprasteria.nl/newsroom/press-releases/details/sopra-steria-next-predicts",
    "slug": "wwwsoprasterianlnewsroompress-releasesdetailssopra-steria-next-predicts",
    "persona": {
      "name": "The_BENELUX_Technology_Innovation_Leader",
      "description": "Unknown Persona (This persona encompasses Chief Technology Officers (CTOs), Chief Digital Officers (CDOs), and their C-suite peers, such as Chief Information Officers (CIOs). They are typically strategic business leaders responsible for driving growth and transformation through technology.)"
    },
    "hygiene_scorecard": {
      "tier": "Press",
      "final_score": 7.8,
      "brand_health_index": 6.68,
      "trust_gap": 0.2,
      "audited_ts": "2025-06-21",
      "detailed_scores": {
        "|_corporate_positioning_alignment": {
          "score": 8,
          "rationale": "The press release aligns well with Sopra Steria's positioning as a major European technology player driving business transformation through AI. It showcases their thought leadership and innovative approach to the AI market."
        },
        "brand_differentiation": {
          "score": 9,
          "rationale": "The unique AI market segmentation methodology introduced in the study (AI for Machines, Processes, Humans, Software) clearly differentiates Sopra Steria's perspective from generic AI market analyses. This \"strategic compass\" demonstrates their deep understanding of AI's diversity and business impact."
        },
        "value_proposition_clarity": {
          "score": 7,
          "rationale": "For the target C-suite persona, the value proposition of leveraging Sopra Steria's AI expertise to drive growth and transformation comes across, but could be articulated more crisply upfront. The discussion of challenges in deploying AI at scale is highly relevant to their priorities."
        },
        "trust_&_credibility_signals": {
          "score": 8,
          "rationale": "Specific market sizing data and growth projections lend credibility. Quotes from the CEO of Sopra Steria Next and references to the Sopra Steria Group's 40,000 IT professionals provide strong trust indicators. More client proof points or case studies would further boost credibility."
        },
        "call-to-action_effectiveness": {
          "score": 7,
          "rationale": "While the strategic insights and deployment challenges are well-aligned to C-level interests, the press release lacks a clear next step or call-to-action for engaging Sopra Steria to help with their AI journey. Adding a consultation offer or link to relevant resources would improve this."
        }
      },
      "recommendations": []
    },
    "experience_report": {
      "overall_sentiment": "Neutral",
      "engagement_level": "Low",
      "conversion_likelihood": "Low",
      "effective_copy": [
        {
          "text": "\"By combining these four categories, we offer our customers a 360-degree view that aligns AI investments with business priorities, identifies use cases that are mature for deployment and those still in the exploration phase, and accelerates the deployment of AI on a large scale,\" explains Fabrice Asvazadourian.",
          "analysis": "As a CTO/CDO, I appreciate how this methodology aims to provide a holistic view to align AI investments with my business priorities. The focus on identifying mature vs. exploratory use cases and accelerating large-scale deployment directly addresses my key goals and pain points."
        }
      ],
      "ineffective_copy": [
        {
          "text": "\"Beyond focusing on the development of AI algorithms to address priority use cases, the real challenge is to successfully industrialise them. Today, only 1 in 7 algorithms reaches the production phase,\" adds Fabrice Asvazadourian.",
          "analysis": "As a C-suite technology leader, this statistic about the low success rate of AI algorithms reaching production is concerning. However, it lacks context around why this happens and what specific challenges need to be overcome. I need more actionable insights."
        }
      ],
      "first_impression": "",
      "strategic_analysis": ""
    },
    "embeddings_content": {
      "combined_analysis": "HYGIENE SCORECARD:\n# Brand Hygiene Scorecard\n\n**URL:** https://www.soprasteria.nl/newsroom/press-releases/details/sopra-steria-next-predicts\n**Persona:** Unknown Persona (This persona encompasses Chief Technology Officers (CTOs), Chief Digital Officers (CDOs), and their C-suite peers, such as Chief Information Officers (CIOs). They are typically strategic business leaders responsible for driving growth and transformation through technology.)\n**Audited:** 2025-06-21 15:59:52\n\n---\n\n## Overall Assessment\n\n- **Tier/Channel:** Press Release\n- **Final Score:** 7.8/10\n\n---\n\n## Detailed Scoring\n\n| Category | Score | Rationale |\n| -------- | ----- | --------- |\n| Corporate Positioning Alignment | 8 | The press release aligns well with Sopra Steria's positioning as a major European technology player driving business transformation through AI. It showcases their thought leadership and innovative approach to the AI market. |\n| Brand Differentiation | 9 | The unique AI market segmentation methodology introduced in the study (AI for Machines, Processes, Humans, Software) clearly differentiates Sopra Steria's perspective from generic AI market analyses. This \"strategic compass\" demonstrates their deep understanding of AI's diversity and business impact. |\n| Value Proposition Clarity | 7 | For the target C-suite persona, the value proposition of leveraging Sopra Steria's AI expertise to drive growth and transformation comes across, but could be articulated more crisply upfront. The discussion of challenges in deploying AI at scale is highly relevant to their priorities. |\n| Trust & Credibility Signals | 8 | Specific market sizing data and growth projections lend credibility. Quotes from the CEO of Sopra Steria Next and references to the Sopra Steria Group's 40,000 IT professionals provide strong trust indicators. More client proof points or case studies would further boost credibility. |\n| Call-to-Action Effectiveness | 7 | While the strategic insights and deployment challenges are well-aligned to C-level interests, the press release lacks a clear next step or call-to-action for engaging Sopra Steria to help with their AI journey. Adding a consultation offer or link to relevant resources would improve this. |\n\n---\n\n## Summary Rationale\n\nFor the target persona of Chief Technology Officers, Chief Digital Officers, and Chief Information Officers, this press release scores well (7.8/10) in demonstrating Sopra Steria's AI thought leadership and ability to drive strategic business transformation. \n\nThe innovative AI market segmentation methodology is a key strength, providing a differentiated \"strategic compass\" highly relevant to C-suite decision-makers. The content aligns with their priorities around harnessing AI for growth while navigating challenges of deploying at scale.\n\nTo further resonate with this persona, the value proposition could be sharpened and client proof points added to strengthen credibility. Most critically, providing clearer guidance on next steps to engage Sopra Steria's AI expertise would improve the call-to-action effectiveness.\n\n---\n\n## Priority Recommendations\n\n1. **Sharpen the value proposition** - Craft a crisp, C-suite focused statement upfront on how Sopra Steria's AI capabilities and methodology help technology leaders drive growth and transformation.\n\n2. **Strengthen credibility with client proof points** - Add 2-3 brief examples or quotes from CTO/CDO-level clients on how Sopra Steria has helped them harness AI strategically. \n\n3. **Improve call-to-action** - Include a clear next step, such as a consultation offer or link to additional resources, to engage Sopra Steria in applying the AI methodology to their business.\n\nEXPERIENCE REPORT:\n| Finding          | Example from Text | Strategic Analysis (from Persona's View)            |\n| ---------------- | ----------------- | --------------------------------------------------- |\n| Ineffective Copy | \"Beyond focusing on the development of AI algorithms to address priority use cases, the real challenge is to successfully industrialise them. Today, only 1 in 7 algorithms reaches the production phase,\" adds Fabrice Asvazadourian.      | As a C-suite technology leader, this statistic about the low success rate of AI algorithms reaching production is concerning. However, it lacks context around why this happens and what specific challenges need to be overcome. I need more actionable insights.  |\n| Effective Copy   | \"By combining these four categories, we offer our customers a 360-degree view that aligns AI investments with business priorities, identifies use cases that are mature for deployment and those still in the exploration phase, and accelerates the deployment of AI on a large scale,\" explains Fabrice Asvazadourian.   | As a CTO/CDO, I appreciate how this methodology aims to provide a holistic view to align AI investments with my business priorities. The focus on identifying mature vs. exploratory use cases and accelerating large-scale deployment directly addresses my key goals and pain points. |\n\nFirst-Person Analysis:\n\nUpon reviewing this press release about Sopra Steria Next's AI market study, my initial impression is mixed. On one hand, the projected market growth figures and innovative segmentation of the AI market into four key categories provides a useful strategic framework for understanding and investing in AI as a C-suite technology leader. The sector-specific insights and identification of priority use cases also help make the analysis more tangible and applicable to my business context.\n\nHowever, while the content outlines the study's methodology and high-level findings, it lacks depth in terms of the specific challenges, best practices, and proof points I would need to confidently move forward with an AI strategy. Statements like \"only 1 in 7 algorithms reaches the production phase\" surface critical issues but don't provide enough context or solutions to fully address my concerns and build trust. \n\nTo strengthen this content, I would recommend including more executive-level insights, such as real-world case studies of AI success and failure, data-driven benchmarks, and frameworks for overcoming common obstacles like legacy systems integration, talent gaps, and measuring ROI. Spotlighting Sopra Steria Next's specific AI solutions and consulting offerings beyond just the market study would also help establish greater credibility and make a stronger case for partnering with them on AI initiatives.\n\nOverall, this press release succeeds in whetting my appetite and highlighting the transformative potential of AI for my business as a technology leader. However, to fully gain my confidence and drive meaningful next steps, the messaging should go a level deeper in translating these market projections into clear, actionable strategic guidance backed by proven results, particularly in my industry. With some refinement, this could serve as an effective thought leadership piece to open the door to further conversations with the C-suite about operationalizing AI.",
      "key_themes": [
        "trust",
        "innovation"
      ],
      "business_impact": ""
    },
    "metadata": {
      "persona_id": "the_benelux_technology_innovation_leader",
      "page_id": "d83b69a8",
      "tier": "press",
      "final_score": 7.8,
      "domain": "www.soprasteria.nl",
      "content_type": "news",
      "regulatory_frameworks": [],
      "is_benelux": true,
      "has_compliance_content": false,
      "has_security_content": false,
      "compiled_at": "2025-07-03T07:43:07.405285"
    }
  },
  {
    "page_id": "624753c4",
    "url": "https://www.soprasteria.be/industries/financial-services",
    "slug": "wwwsoprasteriabeindustriesfinancial-services",
    "persona": {
      "name": "The_BENELUX_Technology_Innovation_Leader",
      "description": "Unknown Persona (This persona encompasses Chief Technology Officers (CTOs), Chief Digital Officers (CDOs), and their C-suite peers, such as Chief Information Officers (CIOs). They are typically strategic business leaders responsible for driving growth and transformation through technology.)"
    },
    "hygiene_scorecard": {
      "tier": "Industry",
      "final_score": 7.4,
      "brand_health_index": 6.44,
      "trust_gap": 0.4,
      "audited_ts": "2025-06-21",
      "detailed_scores": {
        "|_corporate_positioning_alignment": {
          "score": 8,
          "rationale": "The page reflects Sopra Steria's focus on digital transformation and innovation in the financial services industry. It highlights key priorities like risk management, regulatory compliance, and data protection that align with the company's overall brand positioning. However, the messaging could be further elevated to emphasize the strategic business value delivered."
        },
        "brand_differentiation": {
          "score": 7,
          "rationale": "The content touches on Sopra Steria's industry knowledge and banking solutions, but does not go into great depth on what specifically sets them apart from other technology consulting firms serving the financial sector. More details on their unique methodologies, IP, or client success stories could strengthen differentiation."
        },
        "value_proposition_clarity": {
          "score": 7,
          "rationale": "The page outlines several high-level value propositions around helping banks succeed in the digital era, enhancing customer experience, optimizing performance, and enabling innovation. However, the benefits feel somewhat generic and could be more crisply articulated from the CXO persona's business outcome perspective."
        },
        "trust_&_credibility_signals": {
          "score": 6,
          "rationale": "While the page mentions Sopra Steria's comprehensive support and work with clients, there is a lack of concrete proof points. Including client logos, case study excerpts, awards, analyst recognition or other third-party validation could significantly boost credibility for a C-level audience."
        },
        "call-to-action_effectiveness": {
          "score": 8,
          "rationale": "The \"Let's Talk\" CTA appears prominently in two places, making it easy for the persona to take the next step. The CTA to read the financial crime whitepaper is also relevant. However, the generic contact form could be replaced with a more personalized CXO-focused engagement offer to drive stronger conversions."
        }
      },
      "recommendations": []
    },
    "experience_report": {
      "overall_sentiment": "Neutral",
      "engagement_level": "Low",
      "conversion_likelihood": "Low",
      "effective_copy": [
        {
          "text": "\"Sopra Steria supports banks along the entire value chain, from strategy to operations, enabling them to succeed in the new digital normal.\"",
          "analysis": "As a CTO/CDO, I appreciate that Sopra Steria understands the full scope of digital transformation in banking. Supporting the entire value chain is critical for me to drive end-to-end change. This shows they grasp my strategic mandate."
        },
        {
          "text": "\"Discover actionable strategies to better manage risk, protect your customers, and combat financial crime effectively. Act now to stay ahead of evolving threats.\"",
          "analysis": "Financial crime and risk management are top priorities for me. Calling out \"actionable strategies\" to address these challenges catches my attention. I would engage further to learn what those entail, as staying ahead of threats is paramount."
        }
      ],
      "ineffective_copy": [
        {
          "text": "\"The financial services sector is evolving swiftly as regulatory requirements continually adapt to meet societal needs.\"",
          "analysis": "As a C-suite technology leader, this statement is too vague and generic. It doesn't speak to my specific challenges around balancing innovation with security and compliance. I need more targeted insights."
        },
        {
          "text": "\"Together with our clients, we enhance the customer experience, optimise performance, deliver competitive differentiation, and identify new revenue streams.\"",
          "analysis": "While the outcomes mentioned align with my goals at a high level, there are no specifics on how they achieve this. As a technology leader, I need to understand their unique approach and see proof points to build trust."
        }
      ],
      "first_impression": "",
      "strategic_analysis": ""
    },
    "embeddings_content": {
      "combined_analysis": "HYGIENE SCORECARD:\n# Brand Hygiene Scorecard\n\n**URL:** https://www.soprasteria.be/industries/financial-services\n**Persona:** Unknown Persona (This persona encompasses Chief Technology Officers (CTOs), Chief Digital Officers (CDOs), and their C-suite peers, such as Chief Information Officers (CIOs). They are typically strategic business leaders responsible for driving growth and transformation through technology.)\n**Audited:** 2025-06-21 15:56:54\n\n---\n\n## Overall Assessment\n\n- **Tier/Channel:** Industry Solutions Page \n- **Final Score:** 7.4/10\n\n---\n\n## Detailed Scoring\n\n| Category | Score | Rationale |\n| -------- | ----- | --------- |\n| Corporate Positioning Alignment | 8 | The page reflects Sopra Steria's focus on digital transformation and innovation in the financial services industry. It highlights key priorities like risk management, regulatory compliance, and data protection that align with the company's overall brand positioning. However, the messaging could be further elevated to emphasize the strategic business value delivered. |\n| Brand Differentiation | 7 | The content touches on Sopra Steria's industry knowledge and banking solutions, but does not go into great depth on what specifically sets them apart from other technology consulting firms serving the financial sector. More details on their unique methodologies, IP, or client success stories could strengthen differentiation. |\n| Value Proposition Clarity | 7 | The page outlines several high-level value propositions around helping banks succeed in the digital era, enhancing customer experience, optimizing performance, and enabling innovation. However, the benefits feel somewhat generic and could be more crisply articulated from the CXO persona's business outcome perspective. |\n| Trust & Credibility Signals | 6 | While the page mentions Sopra Steria's comprehensive support and work with clients, there is a lack of concrete proof points. Including client logos, case study excerpts, awards, analyst recognition or other third-party validation could significantly boost credibility for a C-level audience. |\n| Call-to-Action Effectiveness | 8 | The \"Let's Talk\" CTA appears prominently in two places, making it easy for the persona to take the next step. The CTA to read the financial crime whitepaper is also relevant. However, the generic contact form could be replaced with a more personalized CXO-focused engagement offer to drive stronger conversions. |\n\n---\n\n## Summary Rationale\n\nFor a CTO/CDO/CIO persona, this financial services page from Sopra Steria covers many of the right topics at a high level, demonstrating an understanding of the industry's digital transformation priorities. The focus on risk management, compliance, data protection, customer experience, and innovation aligns with the strategic concerns of this audience.\n\nHowever, to fully resonate with a C-suite technology decision maker, the page needs to go deeper in proving Sopra Steria's unique capabilities and value proposition. The current content is professionally presented but feels somewhat generic.\n\nEnhancing the page with more differentiated messaging, client proof points, and thought leadership tailored to the CXO perspective would elevate impact and engagement with this persona. Offering a more personalized next step beyond a standard contact form could also drive stronger conversions.\n\nOverall, the page is a solid foundation but has room for optimization to become a more compelling, credible, and differentiated resource for CTO/CDO/CIO financial services buyers.\n\n---\n\n## Priority Recommendations\n\n1. **Strengthen differentiation** - Highlight unique methodologies, IP, accelerators or client success stories that showcase Sopra Steria's differentiated value for financial services CXO priorities.\n\n2. **Elevate value proposition** - Sharpen the articulation of benefits to focus on the strategic business outcomes that most resonate with the CXO persona (e.g. revenue growth, profitability, time-to-market, etc.)\n\n3. **Inject proof points** - Feature client logos, case study excerpts, awards, analyst quotes or other credible third-party validation to build trust and credibility with a C-level audience.\n\nEXPERIENCE REPORT:\n| Finding          | Example from Text | Strategic Analysis (from Persona's View)            |\n| ---------------- | ----------------- | --------------------------------------------------- |\n| Ineffective Copy | \"The financial services sector is evolving swiftly as regulatory requirements continually adapt to meet societal needs.\" | As a C-suite technology leader, this statement is too vague and generic. It doesn't speak to my specific challenges around balancing innovation with security and compliance. I need more targeted insights. |\n| Effective Copy   | \"Sopra Steria supports banks along the entire value chain, from strategy to operations, enabling them to succeed in the new digital normal.\" | As a CTO/CDO, I appreciate that Sopra Steria understands the full scope of digital transformation in banking. Supporting the entire value chain is critical for me to drive end-to-end change. This shows they grasp my strategic mandate.    |\n| Ineffective Copy | \"Together with our clients, we enhance the customer experience, optimise performance, deliver competitive differentiation, and identify new revenue streams.\" | While the outcomes mentioned align with my goals at a high level, there are no specifics on how they achieve this. As a technology leader, I need to understand their unique approach and see proof points to build trust. |\n| Effective Copy   | \"Discover actionable strategies to better manage risk, protect your customers, and combat financial crime effectively. Act now to stay ahead of evolving threats.\" | Financial crime and risk management are top priorities for me. Calling out \"actionable strategies\" to address these challenges catches my attention. I would engage further to learn what those entail, as staying ahead of threats is paramount. |\n\nAs a C-suite technology executive responsible for driving digital transformation in the BENELUX financial services sector, my first impression of this Sopra Steria webpage is mixed. On one hand, they demonstrate an understanding of the rapid evolution and regulatory pressures facing my industry. Acknowledging the shift to digital servicing and its impact on customer expectations resonates with the drivers behind my transformation agenda. \n\nHowever, while the page alludes to their comprehensive support \"along the entire value chain, from strategy to operations\", the lack of specifics leaves me questioning what differentiates their approach. As a leader balancing aggressive innovation with the need for security and compliance, I need to see more substantive proof points and client results to build trust. Generalities about enhancing customer experience and optimizing performance don't give me confidence they can deliver the \"Confident Momentum\" I require.\n\nThe most promising content is around their expertise in risk management, regulatory compliance, data protection and combating financial crime. These are critical focus areas that I expect my transformation partners to have deep competency in. Calling out \"actionable strategies\" piques my interest, but needs to be backed up with client stories, thought leadership and clearer articulation of their capabilities. Absent those specifics, the impact of this page is limited - it doesn't give me enough reason to believe Sopra Steria is the right partner to help shape the future of my business through technology. To strengthen this page, I recommend adding more targeted proof points, client results and perspectives that speak directly to the C-suite technology leader's unique challenges and aspirations. Enhancing credibility and trust needs to be the priority for this audience.",
      "key_themes": [
        "trust",
        "security",
        "compliance",
        "innovation",
        "risk"
      ],
      "business_impact": ""
    },
    "metadata": {
      "persona_id": "the_benelux_technology_innovation_leader",
      "page_id": "624753c4",
      "tier": "industry",
      "final_score": 7.4,
      "domain": "www.soprasteria.be",
      "content_type": "service",
      "regulatory_frameworks": [
        "MIFID"
      ],
      "is_benelux": true,
      "has_compliance_content": true,
      "has_security_content": true,
      "compiled_at": "2025-07-03T07:43:07.405971"
    }
  }
]